{
  "schemaVersion": 1,
  "counts": {
    "total": 63,
    "active": 19,
    "archived": 44
  },
  "sources": [
    {
      "id": "6b9c558e-87e1-43c3-ab50-0581284465a7",
      "notionPageId": "3a0157fd-4777-810b-a955-fff3fac81bd3",
      "title": "Ornamental design",
      "creator": "Paul Flindt",
      "year": "n.d.",
      "type": "Art Institute of Chicago",
      "era": "Undated & Other",
      "region": "Germany",
      "url": "https://www.artic.edu/artworks/108932",
      "imageUrl": "https://www.artic.edu/iiif/2/c979223c-580a-70dc-e8cc-f3168f40c079/full/600,/0/default.jpg",
      "status": "to_read",
      "notionStatus": "Archived",
      "archivedAt": "2026-07-21T16:05:08.641Z",
      "notes": "",
      "createdAt": "2026-07-21T16:05:08.641Z",
      "updatedAt": "2026-07-21T16:05:08.641Z"
    },
    {
      "id": "45c00669-f92d-4269-95ec-07e61cf04821",
      "notionPageId": "3a0157fd-4777-811b-8b78-f7e4f5642426",
      "title": "Design for an Alcove with a Coat of Arms Flanked by Putti",
      "creator": "Giovanni Battista Foggini",
      "year": "1652–1725",
      "type": "The Met",
      "era": "Baroque (17th c.)",
      "region": "Italian (Florence)",
      "url": "https://www.metmuseum.org/art/collection/search/348688",
      "imageUrl": "https://images.metmuseum.org/CRDImages/dp/web-large/DP809752.jpg",
      "status": "to_read",
      "notionStatus": "Archived",
      "archivedAt": "2026-07-21T16:05:08.641Z",
      "notes": "",
      "createdAt": "2026-07-21T16:05:08.642Z",
      "updatedAt": "2026-07-21T16:05:08.642Z"
    },
    {
      "id": "f505b1b8-1cdf-4b43-93f4-9ba1836e4c58",
      "notionPageId": "3a0157fd-4777-8183-b98b-d926d126b643",
      "title": "Design for a Frieze with Putto and Acanthus Scroll",
      "creator": "Anonymous, French",
      "year": "17th century",
      "type": "The Met",
      "era": "Baroque (17th c.)",
      "region": "French",
      "url": "https://www.metmuseum.org/art/collection/search/676592",
      "imageUrl": "https://images.metmuseum.org/CRDImages/dp/web-large/DP838032.jpg",
      "status": "to_read",
      "notionStatus": "Active",
      "archivedAt": null,
      "notes": "",
      "createdAt": "2026-07-21T16:05:08.642Z",
      "updatedAt": "2026-07-21T16:05:08.642Z"
    },
    {
      "id": "c2f04e91-67ee-496b-b253-e7a8e295a406",
      "notionPageId": "3a0157fd-4777-8185-aaed-de6f5cc39ea8",
      "title": "Ornament Design (German, 17th century)",
      "creator": "Anonymous, German",
      "year": "17th century",
      "type": "The Met",
      "era": "Baroque (17th c.)",
      "region": "German",
      "url": "https://www.metmuseum.org/art/collection/search/383958",
      "imageUrl": "https://images.metmuseum.org/CRDImages/dp/web-large/DP804528.jpg",
      "status": "to_read",
      "notionStatus": "Archived",
      "archivedAt": "2026-07-21T16:05:08.642Z",
      "notes": "",
      "createdAt": "2026-07-21T16:05:08.642Z",
      "updatedAt": "2026-07-21T16:05:08.642Z"
    },
    {
      "id": "fa1a5fff-0e9b-4b5e-8ba6-f5996c1650b4",
      "notionPageId": "3a0157fd-4777-81b4-ae7c-f1c3ebe41597",
      "title": "Design for a Chandelier with Acanthus, Grape, and Palmette Motifs",
      "creator": "Anonymous, French",
      "year": "19th century",
      "type": "The Met",
      "era": "19th-Century Revival & Historicism",
      "region": "French",
      "url": "https://www.metmuseum.org/art/collection/search/359625",
      "imageUrl": "https://images.metmuseum.org/CRDImages/dp/web-large/DP809360.jpg",
      "status": "to_read",
      "notionStatus": "Active",
      "archivedAt": null,
      "notes": "",
      "createdAt": "2026-07-21T16:05:08.643Z",
      "updatedAt": "2026-07-21T16:05:08.643Z"
    },
    {
      "id": "be68c1e3-0e17-401b-8a4c-5e8872ed23e4",
      "notionPageId": "3a0157fd-4777-81e8-b377-d77e3f7b33de",
      "title": "Ornament Design with Vases (Designs for Various Ornaments, pl. 38)",
      "creator": "Michelangelo Pergolesi",
      "year": "February 29, 1782",
      "type": "The Met",
      "era": "Rococo & Neoclassical (18th c.)",
      "region": "England",
      "url": "https://www.metmuseum.org/art/collection/search/733984",
      "imageUrl": "https://images.metmuseum.org/CRDImages/dp/web-large/DP104571.jpg",
      "status": "to_read",
      "notionStatus": "Archived",
      "archivedAt": "2026-07-21T16:05:08.643Z",
      "notes": "",
      "createdAt": "2026-07-21T16:05:08.643Z",
      "updatedAt": "2026-07-21T16:05:08.643Z"
    },
    {
      "id": "8259e1ab-e8e0-4c36-a48c-5996bbced4c8",
      "notionPageId": "3a1157fd-4777-8102-bd23-e24c9a0f7ccf",
      "title": "Floral Designs and Floral Bands",
      "creator": "Giacomo Cavenezia",
      "year": "1784",
      "type": "Cleveland Museum of Art",
      "era": "Rococo & Neoclassical (18th c.)",
      "region": "Italian",
      "url": "https://www.clevelandart.org/art/1952.291",
      "imageUrl": "https://openaccess-cdn.clevelandart.org/1952.291/1952.291_web.jpg",
      "status": "to_read",
      "notionStatus": "Archived",
      "archivedAt": "2026-07-21T16:05:08.615Z",
      "notes": "",
      "createdAt": "2026-07-21T16:05:08.616Z",
      "updatedAt": "2026-07-21T16:05:08.616Z"
    },
    {
      "id": "2ebdb1cf-985a-4661-90d7-c13d981f23d7",
      "notionPageId": "3a1157fd-4777-8106-a34d-c14631914e6a",
      "title": "New Suite of Portfolios of Flowers Ideal to Use for Designing and Painting: Floral Fantasies",
      "creator": "Anne Allen",
      "year": "c. 1796",
      "type": "Cleveland Museum of Art",
      "era": "Rococo & Neoclassical (18th c.)",
      "region": "British",
      "url": "https://www.clevelandart.org/art/1968.38",
      "imageUrl": "https://openaccess-cdn.clevelandart.org/1968.38/1968.38_web.jpg",
      "status": "to_read",
      "notionStatus": "Archived",
      "archivedAt": "2026-07-21T16:05:08.612Z",
      "notes": "",
      "createdAt": "2026-07-21T16:05:08.613Z",
      "updatedAt": "2026-07-21T16:05:08.613Z"
    },
    {
      "id": "bb5005b3-234c-4395-aa26-a1e87f19d81f",
      "notionPageId": "3a1157fd-4777-810b-9a50-f7b1c47c6a71",
      "title": "Sketches for Grotesque Wall Decorations",
      "creator": "Girolamo da Carpi (Girolamo Sellari)",
      "year": "1501–56",
      "type": "The Met",
      "era": "Renaissance & Earlier (pre-1600)",
      "region": null,
      "url": "https://www.metmuseum.org/art/collection/search/344680",
      "imageUrl": "https://images.metmuseum.org/CRDImages/dp/original/DP810061.jpg",
      "status": "to_read",
      "notionStatus": "Archived",
      "archivedAt": "2026-07-21T16:05:08.631Z",
      "notes": "",
      "createdAt": "2026-07-21T16:05:08.631Z",
      "updatedAt": "2026-07-21T16:05:08.631Z"
    },
    {
      "id": "b1bf046a-29f1-4fba-9079-fb8b34066cd8",
      "notionPageId": "3a1157fd-4777-810d-b207-f8270a5227aa",
      "title": "Autumn Flower and Sparrow",
      "creator": "Utagawa Hiroshige",
      "year": "c. 1835",
      "type": "Art Institute of Chicago",
      "era": "19th-Century Revival & Historicism",
      "region": "Japanese",
      "url": "https://www.artic.edu/artworks/56236",
      "imageUrl": "https://www.artic.edu/iiif/2/e22f4909-4ec3-fd7b-3959-eb8529baccce/full/843,/0/default.jpg",
      "status": "to_read",
      "notionStatus": "Archived",
      "archivedAt": "2026-07-21T16:05:08.609Z",
      "notes": "",
      "createdAt": "2026-07-21T16:05:08.610Z",
      "updatedAt": "2026-07-21T16:05:08.610Z"
    },
    {
      "id": "234fa152-a6b5-4e6e-9779-b3db914a4fff",
      "notionPageId": "3a1157fd-4777-8111-a8cf-e09295a3d804",
      "title": "Floral Designs with a Blue Bird",
      "creator": "Giacomo Cavenezia",
      "year": "c. 1773/74",
      "type": "Cleveland Museum of Art",
      "era": "Rococo & Neoclassical (18th c.)",
      "region": "Italian",
      "url": "https://www.clevelandart.org/art/1952.287",
      "imageUrl": "https://openaccess-cdn.clevelandart.org/1952.287/1952.287_web.jpg",
      "status": "to_read",
      "notionStatus": "Archived",
      "archivedAt": "2026-07-21T16:05:08.616Z",
      "notes": "",
      "createdAt": "2026-07-21T16:05:08.617Z",
      "updatedAt": "2026-07-21T16:05:08.617Z"
    },
    {
      "id": "b7510b88-232a-48b1-8548-681c69aff992",
      "notionPageId": "3a1157fd-4777-8115-8b61-c958c0452d0c",
      "title": "Florentine Woman Wearing a Butterfly Cap and Holding a Hand Warmer",
      "creator": "Jean-Baptiste Greuze",
      "year": "1755",
      "type": "The Met",
      "era": "Rococo & Neoclassical (18th c.)",
      "region": "France",
      "url": "https://www.metmuseum.org/art/collection/search/337252",
      "imageUrl": "https://images.metmuseum.org/CRDImages/dp/original/DP806602.jpg",
      "status": "to_read",
      "notionStatus": "Archived",
      "archivedAt": "2026-07-21T16:05:08.618Z",
      "notes": "",
      "createdAt": "2026-07-21T16:05:08.619Z",
      "updatedAt": "2026-07-21T16:05:08.619Z"
    },
    {
      "id": "cdd9c1b5-075a-4e6d-aff4-a1fae3288f2f",
      "notionPageId": "3a1157fd-4777-811a-80ef-e745e23bbe9b",
      "title": "Grotesque with a Victory Figure Under an Overgrown Pergola",
      "creator": "Anonymous, Italian, 16th century",
      "year": "1540 after",
      "type": "The Met",
      "era": "Renaissance & Earlier (pre-1600)",
      "region": null,
      "url": "https://www.metmuseum.org/art/collection/search/407178",
      "imageUrl": "https://images.metmuseum.org/CRDImages/dp/original/DP804967.jpg",
      "status": "to_read",
      "notionStatus": "Active",
      "archivedAt": null,
      "notes": "",
      "createdAt": "2026-07-21T16:05:08.629Z",
      "updatedAt": "2026-07-21T16:05:08.629Z"
    },
    {
      "id": "c157c655-22c5-4353-b4e2-c9076f3a5575",
      "notionPageId": "3a1157fd-4777-811d-94d2-e31d9d69768e",
      "title": "Grotesque with an Architectural Structure with a Young Boy on a Bed, Holding a Snake",
      "creator": "Anonymous, Italian, 16th century",
      "year": "1540 after",
      "type": "The Met",
      "era": "Renaissance & Earlier (pre-1600)",
      "region": null,
      "url": "https://www.metmuseum.org/art/collection/search/407173",
      "imageUrl": "https://images.metmuseum.org/CRDImages/dp/original/DP804961.jpg",
      "status": "to_read",
      "notionStatus": "Archived",
      "archivedAt": "2026-07-21T16:05:08.626Z",
      "notes": "",
      "createdAt": "2026-07-21T16:05:08.627Z",
      "updatedAt": "2026-07-21T16:05:08.627Z"
    },
    {
      "id": "4b8d4c48-ee63-4573-b4de-041c63d12afc",
      "notionPageId": "3a1157fd-4777-8125-a5ea-ceba2283dfcb",
      "title": "Floral Designs with Two Birds",
      "creator": "Giacomo Cavenezia",
      "year": "1774",
      "type": "Cleveland Museum of Art",
      "era": "Rococo & Neoclassical (18th c.)",
      "region": "Italian",
      "url": "https://www.clevelandart.org/art/1952.289",
      "imageUrl": "https://openaccess-cdn.clevelandart.org/1952.289/1952.289_web.jpg",
      "status": "to_read",
      "notionStatus": "Archived",
      "archivedAt": "2026-07-21T16:05:08.617Z",
      "notes": "",
      "createdAt": "2026-07-21T16:05:08.617Z",
      "updatedAt": "2026-07-21T16:05:08.617Z"
    },
    {
      "id": "0f8cd2f7-8c42-4934-90e0-4cb2a90938fc",
      "notionPageId": "3a1157fd-4777-8126-896b-cc4dbc52539e",
      "title": "Design for a Hall Lamp",
      "creator": "Lamqua",
      "year": "ca. 1800–1810",
      "type": "The Met",
      "era": "19th-Century Revival & Historicism",
      "region": null,
      "url": "https://www.metmuseum.org/art/collection/search/428554",
      "imageUrl": "https://images.metmuseum.org/CRDImages/dp/original/DP830851.jpg",
      "status": "to_read",
      "notionStatus": "Active",
      "archivedAt": null,
      "notes": "",
      "createdAt": "2026-07-21T16:05:08.639Z",
      "updatedAt": "2026-07-21T16:05:08.639Z"
    },
    {
      "id": "8e339430-f131-4e8c-8339-db78dd232ce0",
      "notionPageId": "3a1157fd-4777-8126-b6cd-c5f15dbe66ea",
      "title": "Candelabra Grotesque with a Large Vase Flanked by Sphinxes",
      "creator": "Anonymous, Italian, 16th century",
      "year": "1540 after",
      "type": "The Met",
      "era": "Renaissance & Earlier (pre-1600)",
      "region": null,
      "url": "https://www.metmuseum.org/art/collection/search/407174",
      "imageUrl": "https://images.metmuseum.org/CRDImages/dp/original/DP804962.jpg",
      "status": "to_read",
      "notionStatus": "Archived",
      "archivedAt": "2026-07-21T16:05:08.627Z",
      "notes": "",
      "createdAt": "2026-07-21T16:05:08.627Z",
      "updatedAt": "2026-07-21T16:05:08.627Z"
    },
    {
      "id": "21f84061-3b19-4e40-9cd2-cf3cf7a8e71f",
      "notionPageId": "3a1157fd-4777-8127-812b-e188cce46eb6",
      "title": "Candelabra Grotesque Crowned by an Altar in a Small Pavillion",
      "creator": "Anonymous, Italian, 16th century",
      "year": "1540 after",
      "type": "The Met",
      "era": "Renaissance & Earlier (pre-1600)",
      "region": null,
      "url": "https://www.metmuseum.org/art/collection/search/407175",
      "imageUrl": "https://images.metmuseum.org/CRDImages/dp/original/DP804963.jpg",
      "status": "to_read",
      "notionStatus": "Archived",
      "archivedAt": "2026-07-21T16:05:08.629Z",
      "notes": "",
      "createdAt": "2026-07-21T16:05:08.629Z",
      "updatedAt": "2026-07-21T16:05:08.629Z"
    },
    {
      "id": "7bface08-8d9c-4eb4-b211-e2b9c1d830d7",
      "notionPageId": "3a1157fd-4777-8127-9dd0-c9a5d2d5930b",
      "title": "Flower Embroidery Design for Silk Manufactory of Lyon",
      "creator": "Jean Baptiste Pillement",
      "year": "c. 1790",
      "type": "Cleveland Museum of Art",
      "era": "Rococo & Neoclassical (18th c.)",
      "region": "French",
      "url": "https://www.clevelandart.org/art/2019.67",
      "imageUrl": "https://openaccess-cdn.clevelandart.org/2019.67/2019.67_web.jpg",
      "status": "to_read",
      "notionStatus": "Archived",
      "archivedAt": "2026-07-21T16:05:08.614Z",
      "notes": "",
      "createdAt": "2026-07-21T16:05:08.614Z",
      "updatedAt": "2026-07-21T16:05:08.614Z"
    },
    {
      "id": "fcffa192-4d14-4b24-80dc-5156df01187f",
      "notionPageId": "3a1157fd-4777-812a-9ded-f8a2e53e4360",
      "title": "Leaf from Aedes Walpolianae mounted with two drawings: (a): Salon Chimney, Houghton Hall, Norfolk, Elevation; (b): Salon Ceiling, Houghton Hall, Norfolk",
      "creator": "Isaac Ware",
      "year": "1735",
      "type": "The Met",
      "era": "Rococo & Neoclassical (18th c.)",
      "region": null,
      "url": "https://www.metmuseum.org/art/collection/search/424135",
      "imageUrl": "https://images.metmuseum.org/CRDImages/dp/original/DP829085.jpg",
      "status": "to_read",
      "notionStatus": "Active",
      "archivedAt": null,
      "notes": "",
      "createdAt": "2026-07-21T16:05:08.633Z",
      "updatedAt": "2026-07-21T16:05:08.633Z"
    },
    {
      "id": "9472dfc0-f919-4139-920f-db6cb4f10128",
      "notionPageId": "3a1157fd-4777-8135-acfe-e8ca97e73f78",
      "title": "Candelabra Grotesque with a Naked Boy in a Strapwork Contraption",
      "creator": "Anonymous, Italian, 16th century",
      "year": "1540 after",
      "type": "The Met",
      "era": "Renaissance & Earlier (pre-1600)",
      "region": null,
      "url": "https://www.metmuseum.org/art/collection/search/407168",
      "imageUrl": "https://images.metmuseum.org/CRDImages/dp/original/DP804953.jpg",
      "status": "to_read",
      "notionStatus": "Archived",
      "archivedAt": "2026-07-21T16:05:08.630Z",
      "notes": "",
      "createdAt": "2026-07-21T16:05:08.630Z",
      "updatedAt": "2026-07-21T16:05:08.630Z"
    },
    {
      "id": "5c2bbca1-914c-4d2c-b8d8-ae690427a233",
      "notionPageId": "3a1157fd-4777-8139-a11c-e89fc51cc9fb",
      "title": "Candelabra Grotesque with a Female Figure in a Niche and Two Sphinxes",
      "creator": "Anonymous, Italian, 16th century",
      "year": "1540 after",
      "type": "The Met",
      "era": "Renaissance & Earlier (pre-1600)",
      "region": null,
      "url": "https://www.metmuseum.org/art/collection/search/407177",
      "imageUrl": "https://images.metmuseum.org/CRDImages/dp/original/DP804966.jpg",
      "status": "to_read",
      "notionStatus": "Archived",
      "archivedAt": "2026-07-21T16:05:08.626Z",
      "notes": "",
      "createdAt": "2026-07-21T16:05:08.626Z",
      "updatedAt": "2026-07-21T16:05:08.626Z"
    },
    {
      "id": "e1c8fe68-88fc-494b-b0a0-cb08d4ac5736",
      "notionPageId": "3a1157fd-4777-813e-bfa3-d13c1158c4a1",
      "title": "Design for a Chimney Piece",
      "creator": "Anonymous, British, 18th century",
      "year": "late 18th century",
      "type": "The Met",
      "era": "Rococo & Neoclassical (18th c.)",
      "region": null,
      "url": "https://www.metmuseum.org/art/collection/search/386753",
      "imageUrl": "https://images.metmuseum.org/CRDImages/dp/original/DP806988.jpg",
      "status": "to_read",
      "notionStatus": "Archived",
      "archivedAt": "2026-07-21T16:05:08.635Z",
      "notes": "",
      "createdAt": "2026-07-21T16:05:08.636Z",
      "updatedAt": "2026-07-21T16:05:08.636Z"
    },
    {
      "id": "f0d7493c-a74c-4c8b-ab7c-dc2f7c69551d",
      "notionPageId": "3a1157fd-4777-813f-ab45-c7ffdb3402ea",
      "title": "Villa of Agostino Chigi (La Farnesina), Rome, north façade, with ornamental detailing (recto); Villa of Agostino Chigi (La Farnesina), Rome, plan and moulding profiles (verso)",
      "creator": "Anonymous, French, 16th century",
      "year": "early to mid-16th century",
      "type": "The Met",
      "era": "Renaissance & Earlier (pre-1600)",
      "region": null,
      "url": "https://www.metmuseum.org/art/collection/search/360503",
      "imageUrl": "https://images.metmuseum.org/CRDImages/dp/original/DP819311.jpg",
      "status": "to_read",
      "notionStatus": "Archived",
      "archivedAt": "2026-07-21T16:05:08.636Z",
      "notes": "",
      "createdAt": "2026-07-21T16:05:08.636Z",
      "updatedAt": "2026-07-21T16:05:08.636Z"
    },
    {
      "id": "79821509-9c24-49f8-afa8-f7ea0f1133ae",
      "notionPageId": "3a1157fd-4777-8149-95a9-cdb5fa712b99",
      "title": "Candelabra Grotesque with a Winged Female Term on a Pedestal",
      "creator": "Anonymous, Italian, 16th century",
      "year": "1540 after",
      "type": "The Met",
      "era": "Renaissance & Earlier (pre-1600)",
      "region": null,
      "url": "https://www.metmuseum.org/art/collection/search/407171",
      "imageUrl": "https://images.metmuseum.org/CRDImages/dp/original/DP804958.jpg",
      "status": "to_read",
      "notionStatus": "Active",
      "archivedAt": null,
      "notes": "",
      "createdAt": "2026-07-21T16:05:08.628Z",
      "updatedAt": "2026-07-21T16:05:08.628Z"
    },
    {
      "id": "79fcf72a-8bba-4915-8195-50298b640f88",
      "notionPageId": "3a1157fd-4777-814a-a82b-da1f0d918bdd",
      "title": "Flower Study",
      "creator": "Harry Fenn",
      "year": "c. 1857–1911",
      "type": "Cleveland Museum of Art",
      "era": "19th-Century Revival & Historicism",
      "region": "American",
      "url": "https://www.clevelandart.org/art/1928.120",
      "imageUrl": "https://openaccess-cdn.clevelandart.org/1928.120/1928.120_web.jpg",
      "status": "to_read",
      "notionStatus": "Archived",
      "archivedAt": "2026-07-21T16:05:08.614Z",
      "notes": "",
      "createdAt": "2026-07-21T16:05:08.615Z",
      "updatedAt": "2026-07-21T16:05:08.615Z"
    },
    {
      "id": "2dc19e04-98c3-40fa-a2ef-d028e130f18a",
      "notionPageId": "3a1157fd-4777-8150-90ed-d8592621814b",
      "title": "Design for an Overdoor or Chimney Piece with an Armorial Trophy and the personification of Victory",
      "creator": "Anonymous, French, 18th century",
      "year": "18th century",
      "type": "The Met",
      "era": "Rococo & Neoclassical (18th c.)",
      "region": null,
      "url": "https://www.metmuseum.org/art/collection/search/346327",
      "imageUrl": "https://images.metmuseum.org/CRDImages/dp/original/DP808748.jpg",
      "status": "to_read",
      "notionStatus": "Archived",
      "archivedAt": "2026-07-21T16:05:08.632Z",
      "notes": "",
      "createdAt": "2026-07-21T16:05:08.633Z",
      "updatedAt": "2026-07-21T16:05:08.633Z"
    },
    {
      "id": "6a0bf55d-529e-4ef7-a55c-0dd150fc71f8",
      "notionPageId": "3a1157fd-4777-8160-979c-f73dfbca80c4",
      "title": "Design for a Chimney Piece",
      "creator": "Anonymous, British, 18th century",
      "year": "18th century",
      "type": "The Met",
      "era": "Rococo & Neoclassical (18th c.)",
      "region": null,
      "url": "https://www.metmuseum.org/art/collection/search/362364",
      "imageUrl": "https://images.metmuseum.org/CRDImages/dp/original/DP806987.jpg",
      "status": "to_read",
      "notionStatus": "Active",
      "archivedAt": null,
      "notes": "",
      "createdAt": "2026-07-21T16:05:08.635Z",
      "updatedAt": "2026-07-21T16:05:08.635Z"
    },
    {
      "id": "ac6fd745-2a96-497a-82da-9768808abe07",
      "notionPageId": "3a1157fd-4777-8164-8935-e6873da61f65",
      "title": "Design for a Wall Monument",
      "creator": "Francesco di Giorgio Martini",
      "year": "ca. 1490",
      "type": "The Met",
      "era": "Renaissance & Earlier (pre-1600)",
      "region": null,
      "url": "https://www.metmuseum.org/art/collection/search/459185",
      "imageUrl": "https://images.metmuseum.org/CRDImages/rl/original/DP324211.jpg",
      "status": "to_read",
      "notionStatus": "Archived",
      "archivedAt": "2026-07-21T16:05:08.638Z",
      "notes": "",
      "createdAt": "2026-07-21T16:05:08.638Z",
      "updatedAt": "2026-07-21T16:05:08.638Z"
    },
    {
      "id": "f9d73940-3e92-4216-9b16-5212c41f30e2",
      "notionPageId": "3a1157fd-4777-8166-97c2-d9638d523728",
      "title": "Design for a Chimney Piece in the Gallery, now Dining Room, Harewood House, Yorkshire (Elevation)",
      "creator": "Robert Adam",
      "year": "ca. 1769",
      "type": "The Met",
      "era": "Rococo & Neoclassical (18th c.)",
      "region": null,
      "url": "https://www.metmuseum.org/art/collection/search/365741",
      "imageUrl": "https://images.metmuseum.org/CRDImages/dp/original/DP800707.jpg",
      "status": "to_read",
      "notionStatus": "Active",
      "archivedAt": null,
      "notes": "",
      "createdAt": "2026-07-21T16:05:08.634Z",
      "updatedAt": "2026-07-21T16:05:08.634Z"
    },
    {
      "id": "5011a01b-1452-4f6f-b799-42e03f4327d8",
      "notionPageId": "3a1157fd-4777-8168-9757-eaaf575b5c50",
      "title": "Design for a Chimney piece decorated with figures of Venus and Cupid",
      "creator": "Emil Wolff",
      "year": "ca. 1835–50",
      "type": "The Met",
      "era": "19th-Century Revival & Historicism",
      "region": null,
      "url": "https://www.metmuseum.org/art/collection/search/676829",
      "imageUrl": "https://images.metmuseum.org/CRDImages/dp/original/DP860287.jpg",
      "status": "to_read",
      "notionStatus": "Archived",
      "archivedAt": "2026-07-21T16:05:08.634Z",
      "notes": "",
      "createdAt": "2026-07-21T16:05:08.634Z",
      "updatedAt": "2026-07-21T16:05:08.634Z"
    },
    {
      "id": "14562338-b150-4790-a456-f60bc6fb8537",
      "notionPageId": "3a1157fd-4777-8174-8dda-c687aeea5714",
      "title": "Ornament",
      "creator": "Alphonse Mucha",
      "year": "1901–2",
      "type": "Cleveland Museum of Art",
      "era": "Modern (20th c.+)",
      "region": "Czech",
      "url": "https://www.clevelandart.org/art/1992.35",
      "imageUrl": "https://openaccess-cdn.clevelandart.org/1992.35/1992.35_web.jpg",
      "status": "to_read",
      "notionStatus": "Active",
      "archivedAt": null,
      "notes": "",
      "createdAt": "2026-07-21T16:05:08.618Z",
      "updatedAt": "2026-07-21T16:05:08.618Z"
    },
    {
      "id": "877b12f8-ee77-4ff9-ad38-5b9993c9d7ee",
      "notionPageId": "3a1157fd-4777-8176-9c2a-cee7652234ea",
      "title": "Design for a Wall Panel or Ceiling with The Virgin and Saints Interceding before Christ for the Souls of the Lost",
      "creator": "Johann Baptist Enderle",
      "year": "1771 or before",
      "type": "The Met",
      "era": "Rococo & Neoclassical (18th c.)",
      "region": "Germany",
      "url": "https://www.metmuseum.org/art/collection/search/393432",
      "imageUrl": "https://images.metmuseum.org/CRDImages/dp/original/DP237820.jpg",
      "status": "to_read",
      "notionStatus": "Archived",
      "archivedAt": "2026-07-21T16:05:08.637Z",
      "notes": "",
      "createdAt": "2026-07-21T16:05:08.637Z",
      "updatedAt": "2026-07-21T16:05:08.637Z"
    },
    {
      "id": "220fb9c2-b496-49c6-bd03-55d0bc932612",
      "notionPageId": "3a1157fd-4777-8184-aabd-e1655c3fec5f",
      "title": "Study of Justice Dispensing Rewards to the Arts (recto); Study of a Lunette and Spandrel (verso)",
      "creator": "Lorenzo de' Ferrari",
      "year": "1680–1744",
      "type": "The Met",
      "era": "Baroque (17th c.)",
      "region": null,
      "url": "https://www.metmuseum.org/art/collection/search/335968",
      "imageUrl": "https://images.metmuseum.org/CRDImages/dp/original/DP809467.jpg",
      "status": "to_read",
      "notionStatus": "Archived",
      "archivedAt": "2026-07-21T16:05:08.620Z",
      "notes": "",
      "createdAt": "2026-07-21T16:05:08.621Z",
      "updatedAt": "2026-07-21T16:05:08.621Z"
    },
    {
      "id": "145badd5-27e1-4adc-b5cf-a9142554fb77",
      "notionPageId": "3a1157fd-4777-818a-8c42-d0ccd1dc4f2c",
      "title": "Ornament with a Palmette",
      "creator": "Sebald Beham",
      "year": "n.d.",
      "type": "Art Institute of Chicago",
      "era": "Renaissance & Earlier (pre-1600)",
      "region": "German",
      "url": "https://www.artic.edu/artworks/95548",
      "imageUrl": "https://www.artic.edu/iiif/2/f1d37607-55f9-a6cf-c460-fcb1ed71cbd2/full/843,/0/default.jpg",
      "status": "to_read",
      "notionStatus": "Active",
      "archivedAt": null,
      "notes": "",
      "createdAt": "2026-07-21T16:05:08.608Z",
      "updatedAt": "2026-07-21T16:05:08.608Z"
    },
    {
      "id": "99cb41a3-0bd6-4015-afc4-67c4dbc8786d",
      "notionPageId": "3a1157fd-4777-8193-b16d-ca9823e8e7ab",
      "title": "Design for a Chimney Place and Study of a Nude Female Figure",
      "creator": "Anonymous, Flemish, 17th century",
      "year": "n.d.",
      "type": "The Met",
      "era": "Renaissance & Earlier (pre-1600)",
      "region": null,
      "url": "https://www.metmuseum.org/art/collection/search/348032",
      "imageUrl": "https://images.metmuseum.org/CRDImages/dp/original/DP802347.jpg",
      "status": "to_read",
      "notionStatus": "Archived",
      "archivedAt": "2026-07-21T16:05:08.634Z",
      "notes": "",
      "createdAt": "2026-07-21T16:05:08.634Z",
      "updatedAt": "2026-07-21T16:05:08.634Z"
    },
    {
      "id": "ad002fbd-0bb0-407c-95c3-d0e318638205",
      "notionPageId": "3a1157fd-4777-8199-9bcc-ec5d46d78dd3",
      "title": "Study of a Seated Woman Seen from Behind (Marie-Gabrielle Capet)",
      "creator": "Adélaïde Labille-Guiard",
      "year": "1789",
      "type": "The Met",
      "era": "Rococo & Neoclassical (18th c.)",
      "region": "France",
      "url": "https://www.metmuseum.org/art/collection/search/383862",
      "imageUrl": "https://images.metmuseum.org/CRDImages/dp/original/DP167476.jpg",
      "status": "to_read",
      "notionStatus": "Archived",
      "archivedAt": "2026-07-21T16:05:08.622Z",
      "notes": "",
      "createdAt": "2026-07-21T16:05:08.622Z",
      "updatedAt": "2026-07-21T16:05:08.622Z"
    },
    {
      "id": "2db57fe1-c2fb-46bb-9f29-d2d1b0bf767f",
      "notionPageId": "3a1157fd-4777-819b-88a5-e97f0c326d6a",
      "title": "Design for a Sofa Seat Cover (?) with an Ornamental Frame Containing a Vase with a Large Bundle of Flowers and Leaves and Decorated with Acanthus Leaves and Two Fleurs de Lys",
      "creator": "Anonymous, French, 19th century",
      "year": "1870–1900 (?)",
      "type": "The Met",
      "era": "19th-Century Revival & Historicism",
      "region": null,
      "url": "https://www.metmuseum.org/art/collection/search/711347",
      "imageUrl": "https://images.metmuseum.org/CRDImages/dp/original/DP889274.jpg",
      "status": "to_read",
      "notionStatus": "Archived",
      "archivedAt": "2026-07-21T16:05:08.639Z",
      "notes": "",
      "createdAt": "2026-07-21T16:05:08.639Z",
      "updatedAt": "2026-07-21T16:05:08.639Z"
    },
    {
      "id": "77870358-031e-44e6-b0f3-dcc07b9fa74a",
      "notionPageId": "3a1157fd-4777-81a6-a939-c3a80862e877",
      "title": "Study of a Kneeling Figure (recto); Design for a Festival Chariot (verso)",
      "creator": "Anonymous, Italian, Florentine, 16th century",
      "year": "1530–40",
      "type": "The Met",
      "era": "Renaissance & Earlier (pre-1600)",
      "region": null,
      "url": "https://www.metmuseum.org/art/collection/search/359449",
      "imageUrl": "https://images.metmuseum.org/CRDImages/dp/original/DP115159.jpg",
      "status": "to_read",
      "notionStatus": "Archived",
      "archivedAt": "2026-07-21T16:05:08.621Z",
      "notes": "",
      "createdAt": "2026-07-21T16:05:08.621Z",
      "updatedAt": "2026-07-21T16:05:08.621Z"
    },
    {
      "id": "62576461-d7eb-4d68-b178-7307f33933fc",
      "notionPageId": "3a1157fd-4777-81ae-8b0a-c800caa7d552",
      "title": "Salon Chimney, Houghton Hall, Norfolk, Elevation",
      "creator": "Isaac Ware",
      "year": "1735",
      "type": "The Met",
      "era": "Rococo & Neoclassical (18th c.)",
      "region": null,
      "url": "https://www.metmuseum.org/art/collection/search/369071",
      "imageUrl": "https://images.metmuseum.org/CRDImages/dp/original/DP829114.jpg",
      "status": "to_read",
      "notionStatus": "Archived",
      "archivedAt": "2026-07-21T16:05:08.635Z",
      "notes": "",
      "createdAt": "2026-07-21T16:05:08.635Z",
      "updatedAt": "2026-07-21T16:05:08.635Z"
    },
    {
      "id": "ecd1f094-b2c9-425e-b79d-3b075dc4b719",
      "notionPageId": "3a1157fd-4777-81af-a4e8-e4a96b26aaf9",
      "title": "Grotesque with a Bacchus Fountain Placed in an Architectural Structure",
      "creator": "Anonymous, Italian, 16th century",
      "year": "1540 after",
      "type": "The Met",
      "era": "Renaissance & Earlier (pre-1600)",
      "region": null,
      "url": "https://www.metmuseum.org/art/collection/search/407170",
      "imageUrl": "https://images.metmuseum.org/CRDImages/dp/original/DP804959.jpg",
      "status": "to_read",
      "notionStatus": "Active",
      "archivedAt": null,
      "notes": "",
      "createdAt": "2026-07-21T16:05:08.630Z",
      "updatedAt": "2026-07-21T16:05:08.630Z"
    },
    {
      "id": "525ac26d-3fd2-4b2c-88ea-01f96ccd0aee",
      "notionPageId": "3a1157fd-4777-81b0-9820-c854e6c0ad12",
      "title": "Design for a Valance with Bundles and Garlands of Flowers and a Monogram Presenting Two Design Variants",
      "creator": "Anonymous, French, 19th century",
      "year": "1870–1900 (?)",
      "type": "The Met",
      "era": "19th-Century Revival & Historicism",
      "region": null,
      "url": "https://www.metmuseum.org/art/collection/search/711322",
      "imageUrl": "https://images.metmuseum.org/CRDImages/dp/original/DP889270.jpg",
      "status": "to_read",
      "notionStatus": "Archived",
      "archivedAt": "2026-07-21T16:05:08.640Z",
      "notes": "",
      "createdAt": "2026-07-21T16:05:08.640Z",
      "updatedAt": "2026-07-21T16:05:08.640Z"
    },
    {
      "id": "9ec09ec6-a462-472c-bb82-69b919719cec",
      "notionPageId": "3a1157fd-4777-81b2-b776-f11ed0612b29",
      "title": "Design for a Chimney Piece",
      "creator": "Anonymous, Italian, 19th century",
      "year": "1800–1900",
      "type": "The Met",
      "era": "19th-Century Revival & Historicism",
      "region": null,
      "url": "https://www.metmuseum.org/art/collection/search/390416",
      "imageUrl": "https://images.metmuseum.org/CRDImages/dp/original/DP803956.jpg",
      "status": "to_read",
      "notionStatus": "Active",
      "archivedAt": null,
      "notes": "",
      "createdAt": "2026-07-21T16:05:08.636Z",
      "updatedAt": "2026-07-21T16:05:08.636Z"
    },
    {
      "id": "15aa99f0-c0fd-4d8c-ab36-88f239d34212",
      "notionPageId": "3a1157fd-4777-81b3-9b26-e954b1a48bab",
      "title": "Design for a Valance with Floral Motifs",
      "creator": "Anonymous, French, 19th century",
      "year": "1870–1900 (?)",
      "type": "The Met",
      "era": "19th-Century Revival & Historicism",
      "region": null,
      "url": "https://www.metmuseum.org/art/collection/search/711224",
      "imageUrl": "https://images.metmuseum.org/CRDImages/dp/original/DP889287.jpg",
      "status": "to_read",
      "notionStatus": "Archived",
      "archivedAt": "2026-07-21T16:05:08.640Z",
      "notes": "",
      "createdAt": "2026-07-21T16:05:08.640Z",
      "updatedAt": "2026-07-21T16:05:08.640Z"
    },
    {
      "id": "a719dbfe-cfc7-47ff-bcf6-f04a3f2dff4c",
      "notionPageId": "3a1157fd-4777-81b3-a815-f80b23d0e56f",
      "title": "Design for Art Nouveau Loveseat with Caning",
      "creator": "Anonymous, French, 19th century",
      "year": "19th century",
      "type": "The Met",
      "era": "19th-Century Revival & Historicism",
      "region": null,
      "url": "https://www.metmuseum.org/art/collection/search/392369",
      "imageUrl": "https://images.metmuseum.org/CRDImages/dp/original/DP812916.jpg",
      "status": "to_read",
      "notionStatus": "Archived",
      "archivedAt": "2026-07-21T16:05:08.620Z",
      "notes": "",
      "createdAt": "2026-07-21T16:05:08.620Z",
      "updatedAt": "2026-07-21T16:05:08.620Z"
    },
    {
      "id": "6ad06866-174a-4426-a7f8-b2d1d62c6d4c",
      "notionPageId": "3a1157fd-4777-81bf-bebd-f191315a9671",
      "title": "Study of Eleven Heads",
      "creator": "Jacques de Gheyn II",
      "year": "late 16th–early 17th century",
      "type": "The Met",
      "era": "Renaissance & Earlier (pre-1600)",
      "region": null,
      "url": "https://www.metmuseum.org/art/collection/search/371145",
      "imageUrl": "https://images.metmuseum.org/CRDImages/dp/original/DP801085.jpg",
      "status": "to_read",
      "notionStatus": "Archived",
      "archivedAt": "2026-07-21T16:05:08.623Z",
      "notes": "",
      "createdAt": "2026-07-21T16:05:08.623Z",
      "updatedAt": "2026-07-21T16:05:08.623Z"
    },
    {
      "id": "b2e7ac7c-c9d3-4c08-b448-493a05891e58",
      "notionPageId": "3a1157fd-4777-81c0-8651-e2e907094817",
      "title": "Design for a tea-pot, verso: design for a covered dish and bowl",
      "creator": "Thomas Fletcher",
      "year": "1800–1866",
      "type": "The Met",
      "era": "19th-Century Revival & Historicism",
      "region": null,
      "url": "https://www.metmuseum.org/art/collection/search/362815",
      "imageUrl": "https://images.metmuseum.org/CRDImages/dp/original/MM60836.jpg",
      "status": "to_read",
      "notionStatus": "Archived",
      "archivedAt": "2026-07-21T16:05:08.637Z",
      "notes": "",
      "createdAt": "2026-07-21T16:05:08.637Z",
      "updatedAt": "2026-07-21T16:05:08.637Z"
    },
    {
      "id": "5996f888-5d27-43ab-ae00-4770856dc437",
      "notionPageId": "3a1157fd-4777-81c0-90f2-ebfe49210626",
      "title": "Designs for Ornamental Motifs and for a Herm Supporting a Chimney Piece",
      "creator": "Moncalvo (Guglielmo Caccia)",
      "year": "1568–1625",
      "type": "The Met",
      "era": "Renaissance & Earlier (pre-1600)",
      "region": null,
      "url": "https://www.metmuseum.org/art/collection/search/340810",
      "imageUrl": "https://images.metmuseum.org/CRDImages/dp/original/DP810689.jpg",
      "status": "to_read",
      "notionStatus": "Active",
      "archivedAt": null,
      "notes": "",
      "createdAt": "2026-07-21T16:05:08.632Z",
      "updatedAt": "2026-07-21T16:05:08.632Z"
    },
    {
      "id": "92a299a4-b66c-49b6-8312-7f9cf12d978f",
      "notionPageId": "3a1157fd-4777-81c0-bb5c-c31b18cfdd61",
      "title": "Design for a Monumental Sacrament House",
      "creator": "Lorenz Lechler",
      "year": "1502",
      "type": "The Met",
      "era": "Renaissance & Earlier (pre-1600)",
      "region": "German",
      "url": "https://www.metmuseum.org/art/collection/search/860992",
      "imageUrl": "https://images.metmuseum.org/CRDImages/cl/original/tr-54ab-2022-1.jpg",
      "status": "to_read",
      "notionStatus": "Active",
      "archivedAt": null,
      "notes": "",
      "createdAt": "2026-07-21T16:05:08.638Z",
      "updatedAt": "2026-07-21T16:05:08.638Z"
    },
    {
      "id": "c5427897-ae51-46d1-bbe5-d3b7c03ca79d",
      "notionPageId": "3a1157fd-4777-81c7-a8ce-ec30f3b4b8e9",
      "title": "Design for a Panel with a Large Bundle of Flowers and Leaves and a Hanging Thin Bundle Containing Gardening Tools Inside an Ornamental Frame Decorated with Thin Garlands of Flowers and Leaves",
      "creator": "Anonymous, French, 19th century",
      "year": "1870–1900 (?)",
      "type": "The Met",
      "era": "19th-Century Revival & Historicism",
      "region": null,
      "url": "https://www.metmuseum.org/art/collection/search/712199",
      "imageUrl": "https://images.metmuseum.org/CRDImages/dp/original/DP889282.jpg",
      "status": "to_read",
      "notionStatus": "Archived",
      "archivedAt": "2026-07-21T16:05:08.640Z",
      "notes": "",
      "createdAt": "2026-07-21T16:05:08.640Z",
      "updatedAt": "2026-07-21T16:05:08.640Z"
    },
    {
      "id": "7f2abcbd-8bb3-4f56-8209-bb3cd301a765",
      "notionPageId": "3a1157fd-4777-81c8-9437-e0acb31ee4d8",
      "title": "Design for the Salon of the Pleasure Pavilion, Favorita, at Ludwigsburg, 1718",
      "creator": "Donato Giuseppe Frisoni",
      "year": "1718",
      "type": "The Met",
      "era": "Rococo & Neoclassical (18th c.)",
      "region": null,
      "url": "https://www.metmuseum.org/art/collection/search/343233",
      "imageUrl": "https://images.metmuseum.org/CRDImages/dp/original/DP820304.jpg",
      "status": "to_read",
      "notionStatus": "Active",
      "archivedAt": null,
      "notes": "",
      "createdAt": "2026-07-21T16:05:08.639Z",
      "updatedAt": "2026-07-21T16:05:08.639Z"
    },
    {
      "id": "1dc815c2-9067-47b0-a7e9-116d6ce09d22",
      "notionPageId": "3a1157fd-4777-81c8-aa93-f0de17c46437",
      "title": "Design for a Title Page with a Coat of Arms (blank) and Two Putti Holding a Crown",
      "creator": "Giovanni Andrea Maglioli",
      "year": "17th century",
      "type": "The Met",
      "era": "Baroque (17th c.)",
      "region": null,
      "url": "https://www.metmuseum.org/art/collection/search/383303",
      "imageUrl": "https://images.metmuseum.org/CRDImages/dp/original/DP804527.jpg",
      "status": "to_read",
      "notionStatus": "Active",
      "archivedAt": null,
      "notes": "",
      "createdAt": "2026-07-21T16:05:08.641Z",
      "updatedAt": "2026-07-21T16:05:08.641Z"
    },
    {
      "id": "78a07487-9ce9-47be-8f5c-ce61f3440849",
      "notionPageId": "3a1157fd-4777-81c9-99f8-f5a3e6f6babf",
      "title": "Spray of Flowers",
      "creator": "L. F. Duruisseau",
      "year": "c. 1774–1800",
      "type": "Cleveland Museum of Art",
      "era": "Rococo & Neoclassical (18th c.)",
      "region": "French",
      "url": "https://www.clevelandart.org/art/1955.475",
      "imageUrl": "https://openaccess-cdn.clevelandart.org/1955.475/1955.475_web.jpg",
      "status": "to_read",
      "notionStatus": "Archived",
      "archivedAt": "2026-07-21T16:05:08.613Z",
      "notes": "",
      "createdAt": "2026-07-21T16:05:08.613Z",
      "updatedAt": "2026-07-21T16:05:08.613Z"
    },
    {
      "id": "51a84651-8c98-4d82-b0b7-e051d5907406",
      "notionPageId": "3a1157fd-4777-81d3-8af7-fec7e7e60d2a",
      "title": "Designs for an Art Nouveau Table and Chair",
      "creator": "Anonymous, French, 19th century",
      "year": "19th century",
      "type": "The Met",
      "era": "19th-Century Revival & Historicism",
      "region": null,
      "url": "https://www.metmuseum.org/art/collection/search/392368",
      "imageUrl": "https://images.metmuseum.org/CRDImages/dp/original/DP812917.jpg",
      "status": "to_read",
      "notionStatus": "Archived",
      "archivedAt": "2026-07-21T16:05:08.619Z",
      "notes": "",
      "createdAt": "2026-07-21T16:05:08.619Z",
      "updatedAt": "2026-07-21T16:05:08.619Z"
    },
    {
      "id": "3fc2babc-39dd-4e6a-9751-c19b93b96ba0",
      "notionPageId": "3a1157fd-4777-81d5-85ca-de3f6615a8e6",
      "title": "Design for a Grotesque Decoration",
      "creator": "Luzio Luzzi (also known as Luzio Romano, Luzio da Todi)",
      "year": "ca. 1543–45",
      "type": "The Met",
      "era": "Renaissance & Earlier (pre-1600)",
      "region": null,
      "url": "https://www.metmuseum.org/art/collection/search/459496",
      "imageUrl": "https://images.metmuseum.org/CRDImages/rl/original/DP-17358-024.jpg",
      "status": "to_read",
      "notionStatus": "Active",
      "archivedAt": null,
      "notes": "",
      "createdAt": "2026-07-21T16:05:08.631Z",
      "updatedAt": "2026-07-21T16:05:08.631Z"
    },
    {
      "id": "ddeadc79-2030-4c38-9e12-40723852e8f2",
      "notionPageId": "3a1157fd-4777-81e2-939b-d5da086aacb5",
      "title": "Design for a Grotesque Wall Decoration",
      "creator": "Perino del Vaga (Pietro Buonaccorsi)",
      "year": "1501–47",
      "type": "The Met",
      "era": "Renaissance & Earlier (pre-1600)",
      "region": null,
      "url": "https://www.metmuseum.org/art/collection/search/346297",
      "imageUrl": "https://images.metmuseum.org/CRDImages/dp/original/DP811055.jpg",
      "status": "to_read",
      "notionStatus": "Archived",
      "archivedAt": "2026-07-21T16:05:08.627Z",
      "notes": "",
      "createdAt": "2026-07-21T16:05:08.628Z",
      "updatedAt": "2026-07-21T16:05:08.628Z"
    },
    {
      "id": "a9b5ba2a-05b5-44ed-9721-52868e5f905a",
      "notionPageId": "3a1157fd-4777-81e6-a6ec-ea16eea9b2d5",
      "title": "Design for an Overdoor or Chimney Piece with an Armorial Trophy and the Figure of Minerva",
      "creator": "Anonymous, French, 18th century",
      "year": "18th century",
      "type": "The Met",
      "era": "Rococo & Neoclassical (18th c.)",
      "region": null,
      "url": "https://www.metmuseum.org/art/collection/search/356113",
      "imageUrl": "https://images.metmuseum.org/CRDImages/dp/original/DP808750.jpg",
      "status": "to_read",
      "notionStatus": "Archived",
      "archivedAt": "2026-07-21T16:05:08.631Z",
      "notes": "",
      "createdAt": "2026-07-21T16:05:08.632Z",
      "updatedAt": "2026-07-21T16:05:08.632Z"
    },
    {
      "id": "26e04987-e410-4e3a-836a-d7c45f5ba39d",
      "notionPageId": "3a1157fd-4777-81e9-9d65-cfb9ce861e73",
      "title": "Sketches of Snails, Flowering Plant",
      "creator": "Édouard Manet",
      "year": "1864/68",
      "type": "Art Institute of Chicago",
      "era": "19th-Century Revival & Historicism",
      "region": "French",
      "url": "https://www.artic.edu/artworks/9485",
      "imageUrl": "https://www.artic.edu/iiif/2/a80f8ca3-3d35-fef0-bd1a-a774519b09da/full/843,/0/default.jpg",
      "status": "to_read",
      "notionStatus": "Active",
      "archivedAt": null,
      "notes": "",
      "createdAt": "2026-07-21T16:05:08.612Z",
      "updatedAt": "2026-07-21T16:05:08.612Z"
    },
    {
      "id": "73b31672-7fae-4c15-90d8-cd485c10558b",
      "notionPageId": "3a1157fd-4777-81f4-b3e4-c18fd504a84b",
      "title": "Design for a Wall Decorated with Grotesque",
      "creator": "Giuseppe Bernardino Bison",
      "year": "1762–1844",
      "type": "The Met",
      "era": "Rococo & Neoclassical (18th c.)",
      "region": null,
      "url": "https://www.metmuseum.org/art/collection/search/342113",
      "imageUrl": "https://images.metmuseum.org/CRDImages/dp/original/DP807984.jpg",
      "status": "to_read",
      "notionStatus": "Active",
      "archivedAt": null,
      "notes": "",
      "createdAt": "2026-07-21T16:05:08.630Z",
      "updatedAt": "2026-07-21T16:05:08.630Z"
    },
    {
      "id": "55bf66ab-9561-46f1-acd0-8ae14bbf9224",
      "notionPageId": "3a1157fd-4777-81f6-81c4-c94cbd4e80df",
      "title": "Cover design for \"Le Jour et la Nuit\"",
      "creator": "Félix Bracquemond",
      "year": "ca. 1879",
      "type": "The Met",
      "era": "19th-Century Revival & Historicism",
      "region": null,
      "url": "https://www.metmuseum.org/art/collection/search/912183",
      "imageUrl": "https://images.metmuseum.org/CRDImages/dp/original/DP-39285-001.jpg",
      "status": "to_read",
      "notionStatus": "Archived",
      "archivedAt": "2026-07-21T16:05:08.637Z",
      "notes": "",
      "createdAt": "2026-07-21T16:05:08.637Z",
      "updatedAt": "2026-07-21T16:05:08.637Z"
    },
    {
      "id": "cec11ebc-1cdf-4c2f-9e54-3f855e6f328d",
      "notionPageId": "3a1157fd-4777-81fa-82bf-e45d91c28b91",
      "title": "Bell-Flower and Dragonfly, from an untitled series of large flowers",
      "creator": "Katsushika Hokusai",
      "year": "c. 1833/34",
      "type": "Art Institute of Chicago",
      "era": "19th-Century Revival & Historicism",
      "region": "Japanese",
      "url": "https://www.artic.edu/artworks/25129",
      "imageUrl": "https://www.artic.edu/iiif/2/960360f3-def7-27e5-6102-6fea8815ff61/full/843,/0/default.jpg",
      "status": "to_read",
      "notionStatus": "Archived",
      "archivedAt": "2026-07-21T16:05:08.610Z",
      "notes": "",
      "createdAt": "2026-07-21T16:05:08.611Z",
      "updatedAt": "2026-07-21T16:05:08.611Z"
    },
    {
      "id": "5030a525-8633-42d2-a443-d79538d39297",
      "notionPageId": "3a1157fd-4777-81fd-a7fd-cff6e9e324cc",
      "title": "Design for a Chair Seat Cover with Floral Motifs",
      "creator": "Anonymous, French, 19th century",
      "year": "1850–1900 (?)",
      "type": "The Met",
      "era": "19th-Century Revival & Historicism",
      "region": null,
      "url": "https://www.metmuseum.org/art/collection/search/711252",
      "imageUrl": "https://images.metmuseum.org/CRDImages/dp/original/DP889275.jpg",
      "status": "to_read",
      "notionStatus": "Archived",
      "archivedAt": "2026-07-21T16:05:08.624Z",
      "notes": "",
      "createdAt": "2026-07-21T16:05:08.626Z",
      "updatedAt": "2026-07-21T16:05:08.626Z"
    },
    {
      "id": "b2726a15-53e2-4d68-971f-7bc966569273",
      "notionPageId": "3a1157fd-4777-81ff-b1f5-edcf1ca31a42",
      "title": "Study of a Jaguar",
      "creator": "John Macallan Swan",
      "year": "1874–1910",
      "type": "The Met",
      "era": "19th-Century Revival & Historicism",
      "region": null,
      "url": "https://www.metmuseum.org/art/collection/search/359244",
      "imageUrl": "https://images.metmuseum.org/CRDImages/dp/original/DT4924.jpg",
      "status": "to_read",
      "notionStatus": "Archived",
      "archivedAt": "2026-07-21T16:05:08.622Z",
      "notes": "",
      "createdAt": "2026-07-21T16:05:08.622Z",
      "updatedAt": "2026-07-21T16:05:08.622Z"
    }
  ]
}
