{
  "schemaVersion": 1,
  "counts": {
    "total": 63,
    "active": 19,
    "archived": 44
  },
  "sources": [
    {
      "id": "a66f8acf-1c90-4d0f-ba0d-a5cbbb4f1826",
      "notionPageId": "3a0157fd-4777-810b-a955-fff3fac81bd3",
      "title": "Ornamental design",
      "creator": "Paul Flindt",
      "year": "n.d.",
      "type": "Art Institute of Chicago",
      "era": "Undated & Other",
      "region": "Germany",
      "url": "https://www.artic.edu/artworks/108932",
      "imageUrl": "https://www.artic.edu/iiif/2/c979223c-580a-70dc-e8cc-f3168f40c079/full/600,/0/default.jpg",
      "status": "to_read",
      "notionStatus": "Archived",
      "archivedAt": "2026-07-19T20:38:36.352Z",
      "notes": "",
      "createdAt": "2026-07-19T20:38:36.352Z",
      "updatedAt": "2026-07-19T20:38:36.352Z"
    },
    {
      "id": "bca20a71-366f-48fd-9ba9-9f57c76d18c7",
      "notionPageId": "3a0157fd-4777-811b-8b78-f7e4f5642426",
      "title": "Design for an Alcove with a Coat of Arms Flanked by Putti",
      "creator": "Giovanni Battista Foggini",
      "year": "1652–1725",
      "type": "The Met",
      "era": "Baroque (17th c.)",
      "region": "Italian (Florence)",
      "url": "https://www.metmuseum.org/art/collection/search/348688",
      "imageUrl": "https://images.metmuseum.org/CRDImages/dp/web-large/DP809752.jpg",
      "status": "to_read",
      "notionStatus": "Archived",
      "archivedAt": "2026-07-19T20:38:36.352Z",
      "notes": "",
      "createdAt": "2026-07-19T20:38:36.353Z",
      "updatedAt": "2026-07-19T20:38:36.353Z"
    },
    {
      "id": "d748de98-1ad8-4ddb-844f-de6a41b578d2",
      "notionPageId": "3a0157fd-4777-8183-b98b-d926d126b643",
      "title": "Design for a Frieze with Putto and Acanthus Scroll",
      "creator": "Anonymous, French",
      "year": "17th century",
      "type": "The Met",
      "era": "Baroque (17th c.)",
      "region": "French",
      "url": "https://www.metmuseum.org/art/collection/search/676592",
      "imageUrl": "https://images.metmuseum.org/CRDImages/dp/web-large/DP838032.jpg",
      "status": "to_read",
      "notionStatus": "Active",
      "archivedAt": null,
      "notes": "",
      "createdAt": "2026-07-19T20:38:36.353Z",
      "updatedAt": "2026-07-19T20:38:36.353Z"
    },
    {
      "id": "53c543cf-d349-4a83-8374-7bcf1fb0c3c7",
      "notionPageId": "3a0157fd-4777-8185-aaed-de6f5cc39ea8",
      "title": "Ornament Design (German, 17th century)",
      "creator": "Anonymous, German",
      "year": "17th century",
      "type": "The Met",
      "era": "Baroque (17th c.)",
      "region": "German",
      "url": "https://www.metmuseum.org/art/collection/search/383958",
      "imageUrl": "https://images.metmuseum.org/CRDImages/dp/web-large/DP804528.jpg",
      "status": "to_read",
      "notionStatus": "Archived",
      "archivedAt": "2026-07-19T20:38:36.353Z",
      "notes": "",
      "createdAt": "2026-07-19T20:38:36.353Z",
      "updatedAt": "2026-07-19T20:38:36.353Z"
    },
    {
      "id": "98aa7c6c-4bd2-45b8-84e2-65fa9ee63fff",
      "notionPageId": "3a0157fd-4777-81b4-ae7c-f1c3ebe41597",
      "title": "Design for a Chandelier with Acanthus, Grape, and Palmette Motifs",
      "creator": "Anonymous, French",
      "year": "19th century",
      "type": "The Met",
      "era": "19th-Century Revival & Historicism",
      "region": "French",
      "url": "https://www.metmuseum.org/art/collection/search/359625",
      "imageUrl": "https://images.metmuseum.org/CRDImages/dp/web-large/DP809360.jpg",
      "status": "to_read",
      "notionStatus": "Active",
      "archivedAt": null,
      "notes": "",
      "createdAt": "2026-07-19T20:38:36.353Z",
      "updatedAt": "2026-07-19T20:38:36.353Z"
    },
    {
      "id": "0e86d3a3-2d35-4e64-a039-86525f791117",
      "notionPageId": "3a0157fd-4777-81e8-b377-d77e3f7b33de",
      "title": "Ornament Design with Vases (Designs for Various Ornaments, pl. 38)",
      "creator": "Michelangelo Pergolesi",
      "year": "February 29, 1782",
      "type": "The Met",
      "era": "Rococo & Neoclassical (18th c.)",
      "region": "England",
      "url": "https://www.metmuseum.org/art/collection/search/733984",
      "imageUrl": "https://images.metmuseum.org/CRDImages/dp/web-large/DP104571.jpg",
      "status": "to_read",
      "notionStatus": "Archived",
      "archivedAt": "2026-07-19T20:38:36.354Z",
      "notes": "",
      "createdAt": "2026-07-19T20:38:36.354Z",
      "updatedAt": "2026-07-19T20:38:36.354Z"
    },
    {
      "id": "1d357b50-20db-43cd-9f1b-90454f5b6801",
      "notionPageId": "3a1157fd-4777-8102-bd23-e24c9a0f7ccf",
      "title": "Floral Designs and Floral Bands",
      "creator": "Giacomo Cavenezia",
      "year": "1784",
      "type": "Cleveland Museum of Art",
      "era": "Rococo & Neoclassical (18th c.)",
      "region": "Italian",
      "url": "https://www.clevelandart.org/art/1952.291",
      "imageUrl": "https://openaccess-cdn.clevelandart.org/1952.291/1952.291_web.jpg",
      "status": "to_read",
      "notionStatus": "Archived",
      "archivedAt": "2026-07-19T20:38:36.329Z",
      "notes": "",
      "createdAt": "2026-07-19T20:38:36.330Z",
      "updatedAt": "2026-07-19T20:38:36.330Z"
    },
    {
      "id": "62193e7a-4124-44b8-85d0-96cbb5d27495",
      "notionPageId": "3a1157fd-4777-8106-a34d-c14631914e6a",
      "title": "New Suite of Portfolios of Flowers Ideal to Use for Designing and Painting: Floral Fantasies",
      "creator": "Anne Allen",
      "year": "c. 1796",
      "type": "Cleveland Museum of Art",
      "era": "Rococo & Neoclassical (18th c.)",
      "region": "British",
      "url": "https://www.clevelandart.org/art/1968.38",
      "imageUrl": "https://openaccess-cdn.clevelandart.org/1968.38/1968.38_web.jpg",
      "status": "to_read",
      "notionStatus": "Archived",
      "archivedAt": "2026-07-19T20:38:36.327Z",
      "notes": "",
      "createdAt": "2026-07-19T20:38:36.327Z",
      "updatedAt": "2026-07-19T20:38:36.327Z"
    },
    {
      "id": "d9b60e18-7f8f-4617-9c4b-42444b7aa15f",
      "notionPageId": "3a1157fd-4777-810b-9a50-f7b1c47c6a71",
      "title": "Sketches for Grotesque Wall Decorations",
      "creator": "Girolamo da Carpi (Girolamo Sellari)",
      "year": "1501–56",
      "type": "The Met",
      "era": "Renaissance & Earlier (pre-1600)",
      "region": null,
      "url": "https://www.metmuseum.org/art/collection/search/344680",
      "imageUrl": "https://images.metmuseum.org/CRDImages/dp/original/DP810061.jpg",
      "status": "to_read",
      "notionStatus": "Archived",
      "archivedAt": "2026-07-19T20:38:36.345Z",
      "notes": "",
      "createdAt": "2026-07-19T20:38:36.345Z",
      "updatedAt": "2026-07-19T20:38:36.345Z"
    },
    {
      "id": "69785938-4d9c-4499-9f5d-4191a29863cd",
      "notionPageId": "3a1157fd-4777-810d-b207-f8270a5227aa",
      "title": "Autumn Flower and Sparrow",
      "creator": "Utagawa Hiroshige",
      "year": "c. 1835",
      "type": "Art Institute of Chicago",
      "era": "19th-Century Revival & Historicism",
      "region": "Japanese",
      "url": "https://www.artic.edu/artworks/56236",
      "imageUrl": "https://www.artic.edu/iiif/2/e22f4909-4ec3-fd7b-3959-eb8529baccce/full/843,/0/default.jpg",
      "status": "to_read",
      "notionStatus": "Archived",
      "archivedAt": "2026-07-19T20:38:36.324Z",
      "notes": "",
      "createdAt": "2026-07-19T20:38:36.324Z",
      "updatedAt": "2026-07-19T20:38:36.324Z"
    },
    {
      "id": "35fd66c1-fc81-4821-b90d-5aa49b075985",
      "notionPageId": "3a1157fd-4777-8111-a8cf-e09295a3d804",
      "title": "Floral Designs with a Blue Bird",
      "creator": "Giacomo Cavenezia",
      "year": "c. 1773/74",
      "type": "Cleveland Museum of Art",
      "era": "Rococo & Neoclassical (18th c.)",
      "region": "Italian",
      "url": "https://www.clevelandart.org/art/1952.287",
      "imageUrl": "https://openaccess-cdn.clevelandart.org/1952.287/1952.287_web.jpg",
      "status": "to_read",
      "notionStatus": "Archived",
      "archivedAt": "2026-07-19T20:38:36.330Z",
      "notes": "",
      "createdAt": "2026-07-19T20:38:36.331Z",
      "updatedAt": "2026-07-19T20:38:36.331Z"
    },
    {
      "id": "6fc507ff-7525-4dcc-ae0d-1dbd7ff94d82",
      "notionPageId": "3a1157fd-4777-8115-8b61-c958c0452d0c",
      "title": "Florentine Woman Wearing a Butterfly Cap and Holding a Hand Warmer",
      "creator": "Jean-Baptiste Greuze",
      "year": "1755",
      "type": "The Met",
      "era": "Rococo & Neoclassical (18th c.)",
      "region": "France",
      "url": "https://www.metmuseum.org/art/collection/search/337252",
      "imageUrl": "https://images.metmuseum.org/CRDImages/dp/original/DP806602.jpg",
      "status": "to_read",
      "notionStatus": "Archived",
      "archivedAt": "2026-07-19T20:38:36.332Z",
      "notes": "",
      "createdAt": "2026-07-19T20:38:36.333Z",
      "updatedAt": "2026-07-19T20:38:36.333Z"
    },
    {
      "id": "e502acaa-5e7e-4761-ae41-b49909115490",
      "notionPageId": "3a1157fd-4777-811a-80ef-e745e23bbe9b",
      "title": "Grotesque with a Victory Figure Under an Overgrown Pergola",
      "creator": "Anonymous, Italian, 16th century",
      "year": "1540 after",
      "type": "The Met",
      "era": "Renaissance & Earlier (pre-1600)",
      "region": null,
      "url": "https://www.metmuseum.org/art/collection/search/407178",
      "imageUrl": "https://images.metmuseum.org/CRDImages/dp/original/DP804967.jpg",
      "status": "to_read",
      "notionStatus": "Active",
      "archivedAt": null,
      "notes": "",
      "createdAt": "2026-07-19T20:38:36.343Z",
      "updatedAt": "2026-07-19T20:38:36.343Z"
    },
    {
      "id": "50fbd74e-8e56-4fc2-acd6-0abe42d90871",
      "notionPageId": "3a1157fd-4777-811d-94d2-e31d9d69768e",
      "title": "Grotesque with an Architectural Structure with a Young Boy on a Bed, Holding a Snake",
      "creator": "Anonymous, Italian, 16th century",
      "year": "1540 after",
      "type": "The Met",
      "era": "Renaissance & Earlier (pre-1600)",
      "region": null,
      "url": "https://www.metmuseum.org/art/collection/search/407173",
      "imageUrl": "https://images.metmuseum.org/CRDImages/dp/original/DP804961.jpg",
      "status": "to_read",
      "notionStatus": "Archived",
      "archivedAt": "2026-07-19T20:38:36.340Z",
      "notes": "",
      "createdAt": "2026-07-19T20:38:36.340Z",
      "updatedAt": "2026-07-19T20:38:36.340Z"
    },
    {
      "id": "18535fd0-438a-4d59-87ee-62951ed7d9f5",
      "notionPageId": "3a1157fd-4777-8125-a5ea-ceba2283dfcb",
      "title": "Floral Designs with Two Birds",
      "creator": "Giacomo Cavenezia",
      "year": "1774",
      "type": "Cleveland Museum of Art",
      "era": "Rococo & Neoclassical (18th c.)",
      "region": "Italian",
      "url": "https://www.clevelandart.org/art/1952.289",
      "imageUrl": "https://openaccess-cdn.clevelandart.org/1952.289/1952.289_web.jpg",
      "status": "to_read",
      "notionStatus": "Archived",
      "archivedAt": "2026-07-19T20:38:36.331Z",
      "notes": "",
      "createdAt": "2026-07-19T20:38:36.331Z",
      "updatedAt": "2026-07-19T20:38:36.331Z"
    },
    {
      "id": "df2cb2cf-46f7-4cb2-8a78-17039ca8e346",
      "notionPageId": "3a1157fd-4777-8126-896b-cc4dbc52539e",
      "title": "Design for a Hall Lamp",
      "creator": "Lamqua",
      "year": "ca. 1800–1810",
      "type": "The Met",
      "era": "19th-Century Revival & Historicism",
      "region": null,
      "url": "https://www.metmuseum.org/art/collection/search/428554",
      "imageUrl": "https://images.metmuseum.org/CRDImages/dp/original/DP830851.jpg",
      "status": "to_read",
      "notionStatus": "Active",
      "archivedAt": null,
      "notes": "",
      "createdAt": "2026-07-19T20:38:36.351Z",
      "updatedAt": "2026-07-19T20:38:36.351Z"
    },
    {
      "id": "8aa059bb-4f6c-4de1-8ea1-4d1ddb263058",
      "notionPageId": "3a1157fd-4777-8126-b6cd-c5f15dbe66ea",
      "title": "Candelabra Grotesque with a Large Vase Flanked by Sphinxes",
      "creator": "Anonymous, Italian, 16th century",
      "year": "1540 after",
      "type": "The Met",
      "era": "Renaissance & Earlier (pre-1600)",
      "region": null,
      "url": "https://www.metmuseum.org/art/collection/search/407174",
      "imageUrl": "https://images.metmuseum.org/CRDImages/dp/original/DP804962.jpg",
      "status": "to_read",
      "notionStatus": "Archived",
      "archivedAt": "2026-07-19T20:38:36.341Z",
      "notes": "",
      "createdAt": "2026-07-19T20:38:36.341Z",
      "updatedAt": "2026-07-19T20:38:36.341Z"
    },
    {
      "id": "b1a2f188-35c6-45ad-bf48-6d3cd0f8e0d7",
      "notionPageId": "3a1157fd-4777-8127-812b-e188cce46eb6",
      "title": "Candelabra Grotesque Crowned by an Altar in a Small Pavillion",
      "creator": "Anonymous, Italian, 16th century",
      "year": "1540 after",
      "type": "The Met",
      "era": "Renaissance & Earlier (pre-1600)",
      "region": null,
      "url": "https://www.metmuseum.org/art/collection/search/407175",
      "imageUrl": "https://images.metmuseum.org/CRDImages/dp/original/DP804963.jpg",
      "status": "to_read",
      "notionStatus": "Archived",
      "archivedAt": "2026-07-19T20:38:36.343Z",
      "notes": "",
      "createdAt": "2026-07-19T20:38:36.343Z",
      "updatedAt": "2026-07-19T20:38:36.343Z"
    },
    {
      "id": "72e7a37b-ffbb-434d-9680-7f6c43240ab1",
      "notionPageId": "3a1157fd-4777-8127-9dd0-c9a5d2d5930b",
      "title": "Flower Embroidery Design for Silk Manufactory of Lyon",
      "creator": "Jean Baptiste Pillement",
      "year": "c. 1790",
      "type": "Cleveland Museum of Art",
      "era": "Rococo & Neoclassical (18th c.)",
      "region": "French",
      "url": "https://www.clevelandart.org/art/2019.67",
      "imageUrl": "https://openaccess-cdn.clevelandart.org/2019.67/2019.67_web.jpg",
      "status": "to_read",
      "notionStatus": "Archived",
      "archivedAt": "2026-07-19T20:38:36.328Z",
      "notes": "",
      "createdAt": "2026-07-19T20:38:36.328Z",
      "updatedAt": "2026-07-19T20:38:36.328Z"
    },
    {
      "id": "5896647d-2c86-42fa-8d9d-8d0a9a57e0b7",
      "notionPageId": "3a1157fd-4777-812a-9ded-f8a2e53e4360",
      "title": "Leaf from Aedes Walpolianae mounted with two drawings: (a): Salon Chimney, Houghton Hall, Norfolk, Elevation; (b): Salon Ceiling, Houghton Hall, Norfolk",
      "creator": "Isaac Ware",
      "year": "1735",
      "type": "The Met",
      "era": "Rococo & Neoclassical (18th c.)",
      "region": null,
      "url": "https://www.metmuseum.org/art/collection/search/424135",
      "imageUrl": "https://images.metmuseum.org/CRDImages/dp/original/DP829085.jpg",
      "status": "to_read",
      "notionStatus": "Active",
      "archivedAt": null,
      "notes": "",
      "createdAt": "2026-07-19T20:38:36.346Z",
      "updatedAt": "2026-07-19T20:38:36.346Z"
    },
    {
      "id": "2e583e58-58ed-4d91-a175-14771168f95f",
      "notionPageId": "3a1157fd-4777-8135-acfe-e8ca97e73f78",
      "title": "Candelabra Grotesque with a Naked Boy in a Strapwork Contraption",
      "creator": "Anonymous, Italian, 16th century",
      "year": "1540 after",
      "type": "The Met",
      "era": "Renaissance & Earlier (pre-1600)",
      "region": null,
      "url": "https://www.metmuseum.org/art/collection/search/407168",
      "imageUrl": "https://images.metmuseum.org/CRDImages/dp/original/DP804953.jpg",
      "status": "to_read",
      "notionStatus": "Archived",
      "archivedAt": "2026-07-19T20:38:36.344Z",
      "notes": "",
      "createdAt": "2026-07-19T20:38:36.344Z",
      "updatedAt": "2026-07-19T20:38:36.344Z"
    },
    {
      "id": "83a70a16-4df7-4cde-80c4-cbcae0f2e64a",
      "notionPageId": "3a1157fd-4777-8139-a11c-e89fc51cc9fb",
      "title": "Candelabra Grotesque with a Female Figure in a Niche and Two Sphinxes",
      "creator": "Anonymous, Italian, 16th century",
      "year": "1540 after",
      "type": "The Met",
      "era": "Renaissance & Earlier (pre-1600)",
      "region": null,
      "url": "https://www.metmuseum.org/art/collection/search/407177",
      "imageUrl": "https://images.metmuseum.org/CRDImages/dp/original/DP804966.jpg",
      "status": "to_read",
      "notionStatus": "Archived",
      "archivedAt": "2026-07-19T20:38:36.340Z",
      "notes": "",
      "createdAt": "2026-07-19T20:38:36.340Z",
      "updatedAt": "2026-07-19T20:38:36.340Z"
    },
    {
      "id": "7d1be65c-98bb-477b-a5ef-15821c71bbb8",
      "notionPageId": "3a1157fd-4777-813e-bfa3-d13c1158c4a1",
      "title": "Design for a Chimney Piece",
      "creator": "Anonymous, British, 18th century",
      "year": "late 18th century",
      "type": "The Met",
      "era": "Rococo & Neoclassical (18th c.)",
      "region": null,
      "url": "https://www.metmuseum.org/art/collection/search/386753",
      "imageUrl": "https://images.metmuseum.org/CRDImages/dp/original/DP806988.jpg",
      "status": "to_read",
      "notionStatus": "Archived",
      "archivedAt": "2026-07-19T20:38:36.348Z",
      "notes": "",
      "createdAt": "2026-07-19T20:38:36.348Z",
      "updatedAt": "2026-07-19T20:38:36.348Z"
    },
    {
      "id": "5e81ca45-8ab7-4619-93b8-e9f4813f324b",
      "notionPageId": "3a1157fd-4777-813f-ab45-c7ffdb3402ea",
      "title": "Villa of Agostino Chigi (La Farnesina), Rome, north façade, with ornamental detailing (recto); Villa of Agostino Chigi (La Farnesina), Rome, plan and moulding profiles (verso)",
      "creator": "Anonymous, French, 16th century",
      "year": "early to mid-16th century",
      "type": "The Met",
      "era": "Renaissance & Earlier (pre-1600)",
      "region": null,
      "url": "https://www.metmuseum.org/art/collection/search/360503",
      "imageUrl": "https://images.metmuseum.org/CRDImages/dp/original/DP819311.jpg",
      "status": "to_read",
      "notionStatus": "Archived",
      "archivedAt": "2026-07-19T20:38:36.349Z",
      "notes": "",
      "createdAt": "2026-07-19T20:38:36.349Z",
      "updatedAt": "2026-07-19T20:38:36.349Z"
    },
    {
      "id": "8eb96f0c-8a11-47c7-8bfb-208448520fe5",
      "notionPageId": "3a1157fd-4777-8149-95a9-cdb5fa712b99",
      "title": "Candelabra Grotesque with a Winged Female Term on a Pedestal",
      "creator": "Anonymous, Italian, 16th century",
      "year": "1540 after",
      "type": "The Met",
      "era": "Renaissance & Earlier (pre-1600)",
      "region": null,
      "url": "https://www.metmuseum.org/art/collection/search/407171",
      "imageUrl": "https://images.metmuseum.org/CRDImages/dp/original/DP804958.jpg",
      "status": "to_read",
      "notionStatus": "Active",
      "archivedAt": null,
      "notes": "",
      "createdAt": "2026-07-19T20:38:36.342Z",
      "updatedAt": "2026-07-19T20:38:36.342Z"
    },
    {
      "id": "ba2090ce-d1df-42ce-a90b-016bd5a5a74d",
      "notionPageId": "3a1157fd-4777-814a-a82b-da1f0d918bdd",
      "title": "Flower Study",
      "creator": "Harry Fenn",
      "year": "c. 1857–1911",
      "type": "Cleveland Museum of Art",
      "era": "19th-Century Revival & Historicism",
      "region": "American",
      "url": "https://www.clevelandart.org/art/1928.120",
      "imageUrl": "https://openaccess-cdn.clevelandart.org/1928.120/1928.120_web.jpg",
      "status": "to_read",
      "notionStatus": "Archived",
      "archivedAt": "2026-07-19T20:38:36.329Z",
      "notes": "",
      "createdAt": "2026-07-19T20:38:36.329Z",
      "updatedAt": "2026-07-19T20:38:36.329Z"
    },
    {
      "id": "c04878ed-ecfa-40f1-8c25-8fe24c498451",
      "notionPageId": "3a1157fd-4777-8150-90ed-d8592621814b",
      "title": "Design for an Overdoor or Chimney Piece with an Armorial Trophy and the personification of Victory",
      "creator": "Anonymous, French, 18th century",
      "year": "18th century",
      "type": "The Met",
      "era": "Rococo & Neoclassical (18th c.)",
      "region": null,
      "url": "https://www.metmuseum.org/art/collection/search/346327",
      "imageUrl": "https://images.metmuseum.org/CRDImages/dp/original/DP808748.jpg",
      "status": "to_read",
      "notionStatus": "Archived",
      "archivedAt": "2026-07-19T20:38:36.346Z",
      "notes": "",
      "createdAt": "2026-07-19T20:38:36.346Z",
      "updatedAt": "2026-07-19T20:38:36.346Z"
    },
    {
      "id": "b009900e-bb87-4d64-94da-25d461d67844",
      "notionPageId": "3a1157fd-4777-8160-979c-f73dfbca80c4",
      "title": "Design for a Chimney Piece",
      "creator": "Anonymous, British, 18th century",
      "year": "18th century",
      "type": "The Met",
      "era": "Rococo & Neoclassical (18th c.)",
      "region": null,
      "url": "https://www.metmuseum.org/art/collection/search/362364",
      "imageUrl": "https://images.metmuseum.org/CRDImages/dp/original/DP806987.jpg",
      "status": "to_read",
      "notionStatus": "Active",
      "archivedAt": null,
      "notes": "",
      "createdAt": "2026-07-19T20:38:36.348Z",
      "updatedAt": "2026-07-19T20:38:36.348Z"
    },
    {
      "id": "ebee378a-a87b-4ebf-a8fe-3ea3f2e13b10",
      "notionPageId": "3a1157fd-4777-8164-8935-e6873da61f65",
      "title": "Design for a Wall Monument",
      "creator": "Francesco di Giorgio Martini",
      "year": "ca. 1490",
      "type": "The Met",
      "era": "Renaissance & Earlier (pre-1600)",
      "region": null,
      "url": "https://www.metmuseum.org/art/collection/search/459185",
      "imageUrl": "https://images.metmuseum.org/CRDImages/rl/original/DP324211.jpg",
      "status": "to_read",
      "notionStatus": "Archived",
      "archivedAt": "2026-07-19T20:38:36.350Z",
      "notes": "",
      "createdAt": "2026-07-19T20:38:36.350Z",
      "updatedAt": "2026-07-19T20:38:36.350Z"
    },
    {
      "id": "c67e8ce5-60b1-4faa-8b56-ab3afa8e320e",
      "notionPageId": "3a1157fd-4777-8166-97c2-d9638d523728",
      "title": "Design for a Chimney Piece in the Gallery, now Dining Room, Harewood House, Yorkshire (Elevation)",
      "creator": "Robert Adam",
      "year": "ca. 1769",
      "type": "The Met",
      "era": "Rococo & Neoclassical (18th c.)",
      "region": null,
      "url": "https://www.metmuseum.org/art/collection/search/365741",
      "imageUrl": "https://images.metmuseum.org/CRDImages/dp/original/DP800707.jpg",
      "status": "to_read",
      "notionStatus": "Active",
      "archivedAt": null,
      "notes": "",
      "createdAt": "2026-07-19T20:38:36.347Z",
      "updatedAt": "2026-07-19T20:38:36.347Z"
    },
    {
      "id": "f6987ca8-bb78-440d-9aa0-697f3b4721eb",
      "notionPageId": "3a1157fd-4777-8168-9757-eaaf575b5c50",
      "title": "Design for a Chimney piece decorated with figures of Venus and Cupid",
      "creator": "Emil Wolff",
      "year": "ca. 1835–50",
      "type": "The Met",
      "era": "19th-Century Revival & Historicism",
      "region": null,
      "url": "https://www.metmuseum.org/art/collection/search/676829",
      "imageUrl": "https://images.metmuseum.org/CRDImages/dp/original/DP860287.jpg",
      "status": "to_read",
      "notionStatus": "Archived",
      "archivedAt": "2026-07-19T20:38:36.347Z",
      "notes": "",
      "createdAt": "2026-07-19T20:38:36.347Z",
      "updatedAt": "2026-07-19T20:38:36.347Z"
    },
    {
      "id": "57918101-e0a4-46f8-9fb1-6c49edefdb9d",
      "notionPageId": "3a1157fd-4777-8174-8dda-c687aeea5714",
      "title": "Ornament",
      "creator": "Alphonse Mucha",
      "year": "1901–2",
      "type": "Cleveland Museum of Art",
      "era": "Modern (20th c.+)",
      "region": "Czech",
      "url": "https://www.clevelandart.org/art/1992.35",
      "imageUrl": "https://openaccess-cdn.clevelandart.org/1992.35/1992.35_web.jpg",
      "status": "to_read",
      "notionStatus": "Active",
      "archivedAt": null,
      "notes": "",
      "createdAt": "2026-07-19T20:38:36.332Z",
      "updatedAt": "2026-07-19T20:38:36.332Z"
    },
    {
      "id": "c8264a61-53cc-402d-a5aa-5e295e683568",
      "notionPageId": "3a1157fd-4777-8176-9c2a-cee7652234ea",
      "title": "Design for a Wall Panel or Ceiling with The Virgin and Saints Interceding before Christ for the Souls of the Lost",
      "creator": "Johann Baptist Enderle",
      "year": "1771 or before",
      "type": "The Met",
      "era": "Rococo & Neoclassical (18th c.)",
      "region": "Germany",
      "url": "https://www.metmuseum.org/art/collection/search/393432",
      "imageUrl": "https://images.metmuseum.org/CRDImages/dp/original/DP237820.jpg",
      "status": "to_read",
      "notionStatus": "Archived",
      "archivedAt": "2026-07-19T20:38:36.349Z",
      "notes": "",
      "createdAt": "2026-07-19T20:38:36.349Z",
      "updatedAt": "2026-07-19T20:38:36.349Z"
    },
    {
      "id": "40de8903-c0fa-4174-bc2a-5214584481a5",
      "notionPageId": "3a1157fd-4777-8184-aabd-e1655c3fec5f",
      "title": "Study of Justice Dispensing Rewards to the Arts (recto); Study of a Lunette and Spandrel (verso)",
      "creator": "Lorenzo de' Ferrari",
      "year": "1680–1744",
      "type": "The Met",
      "era": "Baroque (17th c.)",
      "region": null,
      "url": "https://www.metmuseum.org/art/collection/search/335968",
      "imageUrl": "https://images.metmuseum.org/CRDImages/dp/original/DP809467.jpg",
      "status": "to_read",
      "notionStatus": "Archived",
      "archivedAt": "2026-07-19T20:38:36.334Z",
      "notes": "",
      "createdAt": "2026-07-19T20:38:36.334Z",
      "updatedAt": "2026-07-19T20:38:36.334Z"
    },
    {
      "id": "51a00ef3-e61e-49e4-9db5-a1bc3e33e0a5",
      "notionPageId": "3a1157fd-4777-818a-8c42-d0ccd1dc4f2c",
      "title": "Ornament with a Palmette",
      "creator": "Sebald Beham",
      "year": "n.d.",
      "type": "Art Institute of Chicago",
      "era": "Renaissance & Earlier (pre-1600)",
      "region": "German",
      "url": "https://www.artic.edu/artworks/95548",
      "imageUrl": "https://www.artic.edu/iiif/2/f1d37607-55f9-a6cf-c460-fcb1ed71cbd2/full/843,/0/default.jpg",
      "status": "to_read",
      "notionStatus": "Active",
      "archivedAt": null,
      "notes": "",
      "createdAt": "2026-07-19T20:38:36.322Z",
      "updatedAt": "2026-07-19T20:38:36.322Z"
    },
    {
      "id": "ee562aee-c0f4-40af-9eda-bd534777ef17",
      "notionPageId": "3a1157fd-4777-8193-b16d-ca9823e8e7ab",
      "title": "Design for a Chimney Place and Study of a Nude Female Figure",
      "creator": "Anonymous, Flemish, 17th century",
      "year": "n.d.",
      "type": "The Met",
      "era": "Renaissance & Earlier (pre-1600)",
      "region": null,
      "url": "https://www.metmuseum.org/art/collection/search/348032",
      "imageUrl": "https://images.metmuseum.org/CRDImages/dp/original/DP802347.jpg",
      "status": "to_read",
      "notionStatus": "Archived",
      "archivedAt": "2026-07-19T20:38:36.347Z",
      "notes": "",
      "createdAt": "2026-07-19T20:38:36.347Z",
      "updatedAt": "2026-07-19T20:38:36.347Z"
    },
    {
      "id": "a4705908-68b5-44c4-8819-5b8ff1ec366d",
      "notionPageId": "3a1157fd-4777-8199-9bcc-ec5d46d78dd3",
      "title": "Study of a Seated Woman Seen from Behind (Marie-Gabrielle Capet)",
      "creator": "Adélaïde Labille-Guiard",
      "year": "1789",
      "type": "The Met",
      "era": "Rococo & Neoclassical (18th c.)",
      "region": "France",
      "url": "https://www.metmuseum.org/art/collection/search/383862",
      "imageUrl": "https://images.metmuseum.org/CRDImages/dp/original/DP167476.jpg",
      "status": "to_read",
      "notionStatus": "Archived",
      "archivedAt": "2026-07-19T20:38:36.336Z",
      "notes": "",
      "createdAt": "2026-07-19T20:38:36.336Z",
      "updatedAt": "2026-07-19T20:38:36.336Z"
    },
    {
      "id": "36377e35-5701-4020-93e3-4ed72989e62f",
      "notionPageId": "3a1157fd-4777-819b-88a5-e97f0c326d6a",
      "title": "Design for a Sofa Seat Cover (?) with an Ornamental Frame Containing a Vase with a Large Bundle of Flowers and Leaves and Decorated with Acanthus Leaves and Two Fleurs de Lys",
      "creator": "Anonymous, French, 19th century",
      "year": "1870–1900 (?)",
      "type": "The Met",
      "era": "19th-Century Revival & Historicism",
      "region": null,
      "url": "https://www.metmuseum.org/art/collection/search/711347",
      "imageUrl": "https://images.metmuseum.org/CRDImages/dp/original/DP889274.jpg",
      "status": "to_read",
      "notionStatus": "Archived",
      "archivedAt": "2026-07-19T20:38:36.351Z",
      "notes": "",
      "createdAt": "2026-07-19T20:38:36.351Z",
      "updatedAt": "2026-07-19T20:38:36.351Z"
    },
    {
      "id": "63c0b908-9b0b-4bed-90d4-678c131115a6",
      "notionPageId": "3a1157fd-4777-81a6-a939-c3a80862e877",
      "title": "Study of a Kneeling Figure (recto); Design for a Festival Chariot (verso)",
      "creator": "Anonymous, Italian, Florentine, 16th century",
      "year": "1530–40",
      "type": "The Met",
      "era": "Renaissance & Earlier (pre-1600)",
      "region": null,
      "url": "https://www.metmuseum.org/art/collection/search/359449",
      "imageUrl": "https://images.metmuseum.org/CRDImages/dp/original/DP115159.jpg",
      "status": "to_read",
      "notionStatus": "Archived",
      "archivedAt": "2026-07-19T20:38:36.335Z",
      "notes": "",
      "createdAt": "2026-07-19T20:38:36.335Z",
      "updatedAt": "2026-07-19T20:38:36.335Z"
    },
    {
      "id": "82676ca2-efd2-418d-a71f-2a3c1c6a050d",
      "notionPageId": "3a1157fd-4777-81ae-8b0a-c800caa7d552",
      "title": "Salon Chimney, Houghton Hall, Norfolk, Elevation",
      "creator": "Isaac Ware",
      "year": "1735",
      "type": "The Met",
      "era": "Rococo & Neoclassical (18th c.)",
      "region": null,
      "url": "https://www.metmuseum.org/art/collection/search/369071",
      "imageUrl": "https://images.metmuseum.org/CRDImages/dp/original/DP829114.jpg",
      "status": "to_read",
      "notionStatus": "Archived",
      "archivedAt": "2026-07-19T20:38:36.348Z",
      "notes": "",
      "createdAt": "2026-07-19T20:38:36.348Z",
      "updatedAt": "2026-07-19T20:38:36.348Z"
    },
    {
      "id": "a360eb30-cea1-4cf6-b506-c3b8922c5c83",
      "notionPageId": "3a1157fd-4777-81af-a4e8-e4a96b26aaf9",
      "title": "Grotesque with a Bacchus Fountain Placed in an Architectural Structure",
      "creator": "Anonymous, Italian, 16th century",
      "year": "1540 after",
      "type": "The Met",
      "era": "Renaissance & Earlier (pre-1600)",
      "region": null,
      "url": "https://www.metmuseum.org/art/collection/search/407170",
      "imageUrl": "https://images.metmuseum.org/CRDImages/dp/original/DP804959.jpg",
      "status": "to_read",
      "notionStatus": "Active",
      "archivedAt": null,
      "notes": "",
      "createdAt": "2026-07-19T20:38:36.343Z",
      "updatedAt": "2026-07-19T20:38:36.343Z"
    },
    {
      "id": "4acdfb63-8927-40ee-a41e-d605544ddef9",
      "notionPageId": "3a1157fd-4777-81b0-9820-c854e6c0ad12",
      "title": "Design for a Valance with Bundles and Garlands of Flowers and a Monogram Presenting Two Design Variants",
      "creator": "Anonymous, French, 19th century",
      "year": "1870–1900 (?)",
      "type": "The Met",
      "era": "19th-Century Revival & Historicism",
      "region": null,
      "url": "https://www.metmuseum.org/art/collection/search/711322",
      "imageUrl": "https://images.metmuseum.org/CRDImages/dp/original/DP889270.jpg",
      "status": "to_read",
      "notionStatus": "Archived",
      "archivedAt": "2026-07-19T20:38:36.352Z",
      "notes": "",
      "createdAt": "2026-07-19T20:38:36.352Z",
      "updatedAt": "2026-07-19T20:38:36.352Z"
    },
    {
      "id": "38456fb7-f7a9-4ea8-96c9-f9aa4b10cad7",
      "notionPageId": "3a1157fd-4777-81b2-b776-f11ed0612b29",
      "title": "Design for a Chimney Piece",
      "creator": "Anonymous, Italian, 19th century",
      "year": "1800–1900",
      "type": "The Met",
      "era": "19th-Century Revival & Historicism",
      "region": null,
      "url": "https://www.metmuseum.org/art/collection/search/390416",
      "imageUrl": "https://images.metmuseum.org/CRDImages/dp/original/DP803956.jpg",
      "status": "to_read",
      "notionStatus": "Active",
      "archivedAt": null,
      "notes": "",
      "createdAt": "2026-07-19T20:38:36.348Z",
      "updatedAt": "2026-07-19T20:38:36.348Z"
    },
    {
      "id": "8e506536-b975-4623-84cb-f696529f73a3",
      "notionPageId": "3a1157fd-4777-81b3-9b26-e954b1a48bab",
      "title": "Design for a Valance with Floral Motifs",
      "creator": "Anonymous, French, 19th century",
      "year": "1870–1900 (?)",
      "type": "The Met",
      "era": "19th-Century Revival & Historicism",
      "region": null,
      "url": "https://www.metmuseum.org/art/collection/search/711224",
      "imageUrl": "https://images.metmuseum.org/CRDImages/dp/original/DP889287.jpg",
      "status": "to_read",
      "notionStatus": "Archived",
      "archivedAt": "2026-07-19T20:38:36.351Z",
      "notes": "",
      "createdAt": "2026-07-19T20:38:36.351Z",
      "updatedAt": "2026-07-19T20:38:36.351Z"
    },
    {
      "id": "8a6d8200-65b7-4fc1-b464-5428b69fd2f3",
      "notionPageId": "3a1157fd-4777-81b3-a815-f80b23d0e56f",
      "title": "Design for Art Nouveau Loveseat with Caning",
      "creator": "Anonymous, French, 19th century",
      "year": "19th century",
      "type": "The Met",
      "era": "19th-Century Revival & Historicism",
      "region": null,
      "url": "https://www.metmuseum.org/art/collection/search/392369",
      "imageUrl": "https://images.metmuseum.org/CRDImages/dp/original/DP812916.jpg",
      "status": "to_read",
      "notionStatus": "Archived",
      "archivedAt": "2026-07-19T20:38:36.334Z",
      "notes": "",
      "createdAt": "2026-07-19T20:38:36.334Z",
      "updatedAt": "2026-07-19T20:38:36.334Z"
    },
    {
      "id": "ef4e1fc7-2c59-4080-9a11-2d79ae74fb4c",
      "notionPageId": "3a1157fd-4777-81bf-bebd-f191315a9671",
      "title": "Study of Eleven Heads",
      "creator": "Jacques de Gheyn II",
      "year": "late 16th–early 17th century",
      "type": "The Met",
      "era": "Renaissance & Earlier (pre-1600)",
      "region": null,
      "url": "https://www.metmuseum.org/art/collection/search/371145",
      "imageUrl": "https://images.metmuseum.org/CRDImages/dp/original/DP801085.jpg",
      "status": "to_read",
      "notionStatus": "Archived",
      "archivedAt": "2026-07-19T20:38:36.336Z",
      "notes": "",
      "createdAt": "2026-07-19T20:38:36.336Z",
      "updatedAt": "2026-07-19T20:38:36.336Z"
    },
    {
      "id": "f1414cd0-ff7b-4800-8ea6-d3a613652948",
      "notionPageId": "3a1157fd-4777-81c0-8651-e2e907094817",
      "title": "Design for a tea-pot, verso: design for a covered dish and bowl",
      "creator": "Thomas Fletcher",
      "year": "1800–1866",
      "type": "The Met",
      "era": "19th-Century Revival & Historicism",
      "region": null,
      "url": "https://www.metmuseum.org/art/collection/search/362815",
      "imageUrl": "https://images.metmuseum.org/CRDImages/dp/original/MM60836.jpg",
      "status": "to_read",
      "notionStatus": "Archived",
      "archivedAt": "2026-07-19T20:38:36.349Z",
      "notes": "",
      "createdAt": "2026-07-19T20:38:36.350Z",
      "updatedAt": "2026-07-19T20:38:36.350Z"
    },
    {
      "id": "f13fef9a-6af5-4936-9c83-b420681c405b",
      "notionPageId": "3a1157fd-4777-81c0-90f2-ebfe49210626",
      "title": "Designs for Ornamental Motifs and for a Herm Supporting a Chimney Piece",
      "creator": "Moncalvo (Guglielmo Caccia)",
      "year": "1568–1625",
      "type": "The Met",
      "era": "Renaissance & Earlier (pre-1600)",
      "region": null,
      "url": "https://www.metmuseum.org/art/collection/search/340810",
      "imageUrl": "https://images.metmuseum.org/CRDImages/dp/original/DP810689.jpg",
      "status": "to_read",
      "notionStatus": "Active",
      "archivedAt": null,
      "notes": "",
      "createdAt": "2026-07-19T20:38:36.345Z",
      "updatedAt": "2026-07-19T20:38:36.345Z"
    },
    {
      "id": "d4b9cfcc-db3e-4076-a7a1-dfdcb51a86a8",
      "notionPageId": "3a1157fd-4777-81c0-bb5c-c31b18cfdd61",
      "title": "Design for a Monumental Sacrament House",
      "creator": "Lorenz Lechler",
      "year": "1502",
      "type": "The Met",
      "era": "Renaissance & Earlier (pre-1600)",
      "region": "German",
      "url": "https://www.metmuseum.org/art/collection/search/860992",
      "imageUrl": "https://images.metmuseum.org/CRDImages/cl/original/tr-54ab-2022-1.jpg",
      "status": "to_read",
      "notionStatus": "Active",
      "archivedAt": null,
      "notes": "",
      "createdAt": "2026-07-19T20:38:36.350Z",
      "updatedAt": "2026-07-19T20:38:36.350Z"
    },
    {
      "id": "274064fb-1e01-4ef5-b9c2-a91b2c0a1c08",
      "notionPageId": "3a1157fd-4777-81c7-a8ce-ec30f3b4b8e9",
      "title": "Design for a Panel with a Large Bundle of Flowers and Leaves and a Hanging Thin Bundle Containing Gardening Tools Inside an Ornamental Frame Decorated with Thin Garlands of Flowers and Leaves",
      "creator": "Anonymous, French, 19th century",
      "year": "1870–1900 (?)",
      "type": "The Met",
      "era": "19th-Century Revival & Historicism",
      "region": null,
      "url": "https://www.metmuseum.org/art/collection/search/712199",
      "imageUrl": "https://images.metmuseum.org/CRDImages/dp/original/DP889282.jpg",
      "status": "to_read",
      "notionStatus": "Archived",
      "archivedAt": "2026-07-19T20:38:36.351Z",
      "notes": "",
      "createdAt": "2026-07-19T20:38:36.351Z",
      "updatedAt": "2026-07-19T20:38:36.351Z"
    },
    {
      "id": "cc28e01f-eb18-4105-bd39-a7f3e194a446",
      "notionPageId": "3a1157fd-4777-81c8-9437-e0acb31ee4d8",
      "title": "Design for the Salon of the Pleasure Pavilion, Favorita, at Ludwigsburg, 1718",
      "creator": "Donato Giuseppe Frisoni",
      "year": "1718",
      "type": "The Met",
      "era": "Rococo & Neoclassical (18th c.)",
      "region": null,
      "url": "https://www.metmuseum.org/art/collection/search/343233",
      "imageUrl": "https://images.metmuseum.org/CRDImages/dp/original/DP820304.jpg",
      "status": "to_read",
      "notionStatus": "Active",
      "archivedAt": null,
      "notes": "",
      "createdAt": "2026-07-19T20:38:36.350Z",
      "updatedAt": "2026-07-19T20:38:36.350Z"
    },
    {
      "id": "24544476-09af-4ad8-9843-1bb5c683e878",
      "notionPageId": "3a1157fd-4777-81c8-aa93-f0de17c46437",
      "title": "Design for a Title Page with a Coat of Arms (blank) and Two Putti Holding a Crown",
      "creator": "Giovanni Andrea Maglioli",
      "year": "17th century",
      "type": "The Met",
      "era": "Baroque (17th c.)",
      "region": null,
      "url": "https://www.metmuseum.org/art/collection/search/383303",
      "imageUrl": "https://images.metmuseum.org/CRDImages/dp/original/DP804527.jpg",
      "status": "to_read",
      "notionStatus": "Active",
      "archivedAt": null,
      "notes": "",
      "createdAt": "2026-07-19T20:38:36.352Z",
      "updatedAt": "2026-07-19T20:38:36.352Z"
    },
    {
      "id": "7a97241e-924a-4052-b0cb-9286f60d81ed",
      "notionPageId": "3a1157fd-4777-81c9-99f8-f5a3e6f6babf",
      "title": "Spray of Flowers",
      "creator": "L. F. Duruisseau",
      "year": "c. 1774–1800",
      "type": "Cleveland Museum of Art",
      "era": "Rococo & Neoclassical (18th c.)",
      "region": "French",
      "url": "https://www.clevelandart.org/art/1955.475",
      "imageUrl": "https://openaccess-cdn.clevelandart.org/1955.475/1955.475_web.jpg",
      "status": "to_read",
      "notionStatus": "Archived",
      "archivedAt": "2026-07-19T20:38:36.328Z",
      "notes": "",
      "createdAt": "2026-07-19T20:38:36.328Z",
      "updatedAt": "2026-07-19T20:38:36.328Z"
    },
    {
      "id": "62817a25-f079-4e25-9952-1df0ad362db4",
      "notionPageId": "3a1157fd-4777-81d3-8af7-fec7e7e60d2a",
      "title": "Designs for an Art Nouveau Table and Chair",
      "creator": "Anonymous, French, 19th century",
      "year": "19th century",
      "type": "The Met",
      "era": "19th-Century Revival & Historicism",
      "region": null,
      "url": "https://www.metmuseum.org/art/collection/search/392368",
      "imageUrl": "https://images.metmuseum.org/CRDImages/dp/original/DP812917.jpg",
      "status": "to_read",
      "notionStatus": "Archived",
      "archivedAt": "2026-07-19T20:38:36.333Z",
      "notes": "",
      "createdAt": "2026-07-19T20:38:36.333Z",
      "updatedAt": "2026-07-19T20:38:36.333Z"
    },
    {
      "id": "a717299e-094c-4663-98ba-8ff540103c45",
      "notionPageId": "3a1157fd-4777-81d5-85ca-de3f6615a8e6",
      "title": "Design for a Grotesque Decoration",
      "creator": "Luzio Luzzi (also known as Luzio Romano, Luzio da Todi)",
      "year": "ca. 1543–45",
      "type": "The Met",
      "era": "Renaissance & Earlier (pre-1600)",
      "region": null,
      "url": "https://www.metmuseum.org/art/collection/search/459496",
      "imageUrl": "https://images.metmuseum.org/CRDImages/rl/original/DP-17358-024.jpg",
      "status": "to_read",
      "notionStatus": "Active",
      "archivedAt": null,
      "notes": "",
      "createdAt": "2026-07-19T20:38:36.344Z",
      "updatedAt": "2026-07-19T20:38:36.344Z"
    },
    {
      "id": "de8907a2-cd80-44ac-94f8-63141b922db8",
      "notionPageId": "3a1157fd-4777-81e2-939b-d5da086aacb5",
      "title": "Design for a Grotesque Wall Decoration",
      "creator": "Perino del Vaga (Pietro Buonaccorsi)",
      "year": "1501–47",
      "type": "The Met",
      "era": "Renaissance & Earlier (pre-1600)",
      "region": null,
      "url": "https://www.metmuseum.org/art/collection/search/346297",
      "imageUrl": "https://images.metmuseum.org/CRDImages/dp/original/DP811055.jpg",
      "status": "to_read",
      "notionStatus": "Archived",
      "archivedAt": "2026-07-19T20:38:36.341Z",
      "notes": "",
      "createdAt": "2026-07-19T20:38:36.342Z",
      "updatedAt": "2026-07-19T20:38:36.342Z"
    },
    {
      "id": "a6d0da45-3796-4c0a-823e-d4c8e49710eb",
      "notionPageId": "3a1157fd-4777-81e6-a6ec-ea16eea9b2d5",
      "title": "Design for an Overdoor or Chimney Piece with an Armorial Trophy and the Figure of Minerva",
      "creator": "Anonymous, French, 18th century",
      "year": "18th century",
      "type": "The Met",
      "era": "Rococo & Neoclassical (18th c.)",
      "region": null,
      "url": "https://www.metmuseum.org/art/collection/search/356113",
      "imageUrl": "https://images.metmuseum.org/CRDImages/dp/original/DP808750.jpg",
      "status": "to_read",
      "notionStatus": "Archived",
      "archivedAt": "2026-07-19T20:38:36.345Z",
      "notes": "",
      "createdAt": "2026-07-19T20:38:36.345Z",
      "updatedAt": "2026-07-19T20:38:36.345Z"
    },
    {
      "id": "e5443b46-4161-4f7d-b2bb-f49dbf4a3130",
      "notionPageId": "3a1157fd-4777-81e9-9d65-cfb9ce861e73",
      "title": "Sketches of Snails, Flowering Plant",
      "creator": "Édouard Manet",
      "year": "1864/68",
      "type": "Art Institute of Chicago",
      "era": "19th-Century Revival & Historicism",
      "region": "French",
      "url": "https://www.artic.edu/artworks/9485",
      "imageUrl": "https://www.artic.edu/iiif/2/a80f8ca3-3d35-fef0-bd1a-a774519b09da/full/843,/0/default.jpg",
      "status": "to_read",
      "notionStatus": "Active",
      "archivedAt": null,
      "notes": "",
      "createdAt": "2026-07-19T20:38:36.326Z",
      "updatedAt": "2026-07-19T20:38:36.326Z"
    },
    {
      "id": "f0439508-46d9-4f8b-92fa-2acf257f3b6c",
      "notionPageId": "3a1157fd-4777-81f4-b3e4-c18fd504a84b",
      "title": "Design for a Wall Decorated with Grotesque",
      "creator": "Giuseppe Bernardino Bison",
      "year": "1762–1844",
      "type": "The Met",
      "era": "Rococo & Neoclassical (18th c.)",
      "region": null,
      "url": "https://www.metmuseum.org/art/collection/search/342113",
      "imageUrl": "https://images.metmuseum.org/CRDImages/dp/original/DP807984.jpg",
      "status": "to_read",
      "notionStatus": "Active",
      "archivedAt": null,
      "notes": "",
      "createdAt": "2026-07-19T20:38:36.344Z",
      "updatedAt": "2026-07-19T20:38:36.344Z"
    },
    {
      "id": "b47e0da4-49bd-462a-b668-da90ab290983",
      "notionPageId": "3a1157fd-4777-81f6-81c4-c94cbd4e80df",
      "title": "Cover design for \"Le Jour et la Nuit\"",
      "creator": "Félix Bracquemond",
      "year": "ca. 1879",
      "type": "The Met",
      "era": "19th-Century Revival & Historicism",
      "region": null,
      "url": "https://www.metmuseum.org/art/collection/search/912183",
      "imageUrl": "https://images.metmuseum.org/CRDImages/dp/original/DP-39285-001.jpg",
      "status": "to_read",
      "notionStatus": "Archived",
      "archivedAt": "2026-07-19T20:38:36.349Z",
      "notes": "",
      "createdAt": "2026-07-19T20:38:36.349Z",
      "updatedAt": "2026-07-19T20:38:36.349Z"
    },
    {
      "id": "73685e51-23c3-469d-90bd-56384129dde3",
      "notionPageId": "3a1157fd-4777-81fa-82bf-e45d91c28b91",
      "title": "Bell-Flower and Dragonfly, from an untitled series of large flowers",
      "creator": "Katsushika Hokusai",
      "year": "c. 1833/34",
      "type": "Art Institute of Chicago",
      "era": "19th-Century Revival & Historicism",
      "region": "Japanese",
      "url": "https://www.artic.edu/artworks/25129",
      "imageUrl": "https://www.artic.edu/iiif/2/960360f3-def7-27e5-6102-6fea8815ff61/full/843,/0/default.jpg",
      "status": "to_read",
      "notionStatus": "Archived",
      "archivedAt": "2026-07-19T20:38:36.325Z",
      "notes": "",
      "createdAt": "2026-07-19T20:38:36.325Z",
      "updatedAt": "2026-07-19T20:38:36.325Z"
    },
    {
      "id": "8cf4a66b-280a-4eab-ace3-0cd06f404ffc",
      "notionPageId": "3a1157fd-4777-81fd-a7fd-cff6e9e324cc",
      "title": "Design for a Chair Seat Cover with Floral Motifs",
      "creator": "Anonymous, French, 19th century",
      "year": "1850–1900 (?)",
      "type": "The Met",
      "era": "19th-Century Revival & Historicism",
      "region": null,
      "url": "https://www.metmuseum.org/art/collection/search/711252",
      "imageUrl": "https://images.metmuseum.org/CRDImages/dp/original/DP889275.jpg",
      "status": "to_read",
      "notionStatus": "Archived",
      "archivedAt": "2026-07-19T20:38:36.339Z",
      "notes": "",
      "createdAt": "2026-07-19T20:38:36.339Z",
      "updatedAt": "2026-07-19T20:38:36.339Z"
    },
    {
      "id": "6b7248d0-0686-47df-a934-7d001867cdf5",
      "notionPageId": "3a1157fd-4777-81ff-b1f5-edcf1ca31a42",
      "title": "Study of a Jaguar",
      "creator": "John Macallan Swan",
      "year": "1874–1910",
      "type": "The Met",
      "era": "19th-Century Revival & Historicism",
      "region": null,
      "url": "https://www.metmuseum.org/art/collection/search/359244",
      "imageUrl": "https://images.metmuseum.org/CRDImages/dp/original/DT4924.jpg",
      "status": "to_read",
      "notionStatus": "Archived",
      "archivedAt": "2026-07-19T20:38:36.335Z",
      "notes": "",
      "createdAt": "2026-07-19T20:38:36.335Z",
      "updatedAt": "2026-07-19T20:38:36.335Z"
    }
  ]
}
